[
  {
    "url": "/weibo?q=%23%E8%BF%8E%E6%8E%A5%E5%85%B1%E5%BB%BA%E4%B8%80%E5%B8%A6%E4%B8%80%E8%B7%AF%E6%9B%B4%E9%AB%98%E8%B4%A8%E9%87%8F%E6%9B%B4%E9%AB%98%E6%B0%B4%E5%B9%B3%E7%9A%84%E6%96%B0%E5%8F%91%E5%B1%95%23&Refer=new_time",
    "title": "迎接共建一带一路更高质量更高水平的新发展"
  },
  {
    "url": "/weibo?q=%23%E9%BB%84%E5%AD%90%E9%9F%AC%E5%BE%90%E8%89%BA%E6%B4%8B%E7%BB%93%E5%A9%9A%23&t=31&band_rank=1&Refer=top",
    "title": "黄子韬徐艺洋结婚"
  },
  {
    "url": "/weibo?q=%23%E6%9C%89%E4%BA%BA%E7%94%A8%E8%BF%90%E8%B4%B9%E9%99%A98%E4%B8%AA%E6%9C%88%E9%AA%97%E5%8F%96100%E5%A4%9A%E4%B8%87%23&t=31&band_rank=1&Refer=top",
    "title": "有人用运费险8个月骗取100多万"
  },
  {
    "url": "/weibo?q=%23%E5%B1%B1%E4%B8%9C%E6%89%8B%E9%80%A0%E5%84%92%E9%A3%8E%E6%96%B0%E9%9F%B5%23&t=31&band_rank=3&Refer=top",
    "title": "山东手造儒风新韵"
  },
  {
    "url": "/weibo?q=%23%E6%9F%90%E7%BB%BC%E8%89%BA%E5%9C%A8%E8%A5%BF%E5%AE%89%E4%B8%80%E5%85%AC%E5%9B%AD%E5%BD%95%E5%88%B6%E5%BC%95%E6%B8%B8%E5%AE%A2%E4%B8%8D%E6%BB%A1%23&t=31&band_rank=4&Refer=top",
    "title": "某综艺在西安一公园录制引游客不满"
  },
  {
    "url": "/weibo?q=%23%E5%95%86%E5%AE%B6%E5%A4%A7%E8%A7%84%E6%A8%A1%E5%85%B3%E9%97%AD%E8%BF%90%E8%B4%B9%E9%99%A9%E8%83%8C%E5%90%8E%23&t=31&band_rank=7&Refer=top",
    "title": "商家大规模关闭运费险背后"
  },
  {
    "url": "/weibo?q=%23%E5%BE%90%E8%89%BA%E6%B4%8B%E5%B9%BC%E5%B8%88%E8%B5%84%E6%A0%BC%E8%AF%81%E4%B8%8B%E6%9D%A5%E4%BA%86%23&t=31&band_rank=6&Refer=top",
    "title": "徐艺洋幼师资格证下来了"
  },
  {
    "url": "/weibo?q=%E9%BB%84%E5%AD%90%E9%9F%AC%20%E5%90%83%E5%B8%ADcall%20me&t=31&band_rank=7&Refer=top",
    "title": "黄子韬 吃席call me"
  },
  {
    "url": "/weibo?q=%23%E4%B8%80%E6%95%99%E5%9F%B9%E6%9C%BA%E6%9E%8420%E5%A4%9A%E4%BA%BA%E8%B6%B4%E5%9C%B0%E4%B8%8A%E8%BF%8E%E6%8E%A5%E9%A2%86%E5%AF%BC%23&t=31&band_rank=8&Refer=top",
    "title": "一教培机构20多人趴地上迎接领导"
  },
  {
    "url": "/weibo?q=%23%E7%8B%90%E5%A6%96%E7%AB%B9%E4%B8%9A%E7%AF%87%E6%94%B9%E5%90%8D%E6%B7%AE%E6%B0%B4%E7%AB%B9%E4%BA%AD%23&t=31&band_rank=9&Refer=top",
    "title": "狐妖竹业篇改名淮水竹亭"
  },
  {
    "url": "/weibo?q=%232024%E5%B9%B4%E5%8D%81%E5%A4%A7%E6%B5%81%E8%A1%8C%E8%AF%AD%23&t=31&band_rank=18&Refer=top",
    "title": "2024年十大流行语"
  },
  { "url": "/weibo?q=%E5%BD%92%E5%9B%BD%E5%9B%9B%E5%AD%90&t=31&band_rank=11&Refer=top", "title": "归国四子" },
  {
    "url": "/weibo?q=%23AI%E5%AD%A6%E4%B9%A0%E6%9C%BA%E4%B8%80%E6%9C%AC%E6%AD%A3%E7%BB%8F%E7%9E%8E%E5%88%A4%E4%BD%9C%E4%B8%9A%23&t=31&band_rank=12&Refer=top",
    "title": "AI学习机一本正经瞎判作业"
  },
  {
    "url": "/weibo?q=%23%E8%8D%A3%E8%80%80300%E5%8F%91%E5%B8%83%E4%BC%9A%23&t=31&band_rank=39&Refer=top",
    "title": "荣耀300发布会"
  },
  {
    "url": "/weibo?q=%23%E5%A5%9A%E6%A2%A6%E7%91%B6%E7%8E%B0%E8%BA%AB%E7%A7%81%E7%AB%8B%E5%8C%BB%E9%99%A2%23&t=31&band_rank=14&Refer=top",
    "title": "奚梦瑶现身私立医院"
  },
  {
    "url": "/weibo?q=%23%E8%A7%82%E4%BC%97%E7%9C%8B%E6%97%85%E8%A1%8C%E7%9C%9F%E4%BA%BA%E7%A7%80%E7%9C%8B%E7%9A%84%E6%98%AF%E4%BB%80%E4%B9%88%23&t=31&band_rank=15&Refer=top",
    "title": "观众看旅行真人秀看的是什么"
  },
  {
    "url": "/weibo?q=%23%E9%A6%99%E6%B8%AF97%E5%B9%B4%E5%8D%A1%E6%8B%89OK%E7%BA%B5%E7%81%AB%E6%A1%88%E5%AB%8C%E7%8A%AF%E5%86%85%E5%9C%B0%E8%90%BD%E7%BD%91%23&t=31&band_rank=16&Refer=top",
    "title": "香港97年卡拉OK纵火案嫌犯内地落网"
  },
  {
    "url": "/weibo?q=%23%E7%8E%8B%E6%9A%96%E6%9A%96%E5%BE%8B%E5%B8%88%E5%9B%9E%E5%BA%943000%E4%B8%87%E7%A6%BB%E5%A9%9A%E8%B4%B9%E9%97%AE%E9%A2%98%23&t=31&band_rank=17&Refer=top",
    "title": "王暖暖律师回应3000万离婚费问题"
  },
  {
    "url": "/weibo?q=%2322%E4%B8%87789%E5%8C%B9%E9%A2%86%E5%85%8B%E7%8E%8B%E6%9D%A5%E4%BA%86%23&t=31&band_rank=18&Refer=top",
    "title": "22万789匹领克王来了"
  },
  {
    "url": "/weibo?q=%23%E8%8D%A3%E8%80%80300%E9%95%9C%E5%A4%B4%E4%B8%8B%E7%9A%84%E8%99%9E%E4%B9%A6%E6%AC%A3%23&t=31&band_rank=19&Refer=top",
    "title": "荣耀300镜头下的虞书欣"
  },
  {
    "url": "/weibo?q=%23%E7%BA%A2%E6%97%97%E6%96%B0%E8%83%BD%E6%BA%90%E6%B0%B8%E8%BF%9C%E5%8F%AF%E4%BB%A5%E7%9B%B8%E4%BF%A1%23&t=31&band_rank=20&Refer=top",
    "title": "红旗新能源永远可以相信"
  },
  {
    "url": "/weibo?q=%23%E6%94%B6%E6%8B%BE%E6%94%B6%E6%8B%BE%E5%87%86%E5%A4%87%E6%8A%95%E8%83%8E%E5%90%A7%23&t=31&band_rank=21&Refer=top",
    "title": "收拾收拾准备投胎吧"
  },
  {
    "url": "/weibo?q=%23%E5%B7%B4%E9%BB%8E%E5%9C%A3%E6%AF%8D%E9%99%A2%E6%9C%AC%E5%91%A8%E9%87%8D%E6%96%B0%E5%90%91%E5%85%AC%E4%BC%97%E5%BC%80%E6%94%BE%23&t=31&band_rank=22&Refer=top",
    "title": "巴黎圣母院本周重新向公众开放"
  },
  {
    "url": "/weibo?q=%23%E6%9D%8E%E8%BF%85%E9%9B%B7%E5%9B%9E%E5%BA%94%E8%82%A1%E5%B8%82%E4%B8%8A%E6%B6%A8%E8%83%BD%E4%B8%8D%E8%83%BD%E4%BF%83%E6%B6%88%E8%B4%B9%23&t=31&band_rank=23&Refer=top",
    "title": "李迅雷回应股市上涨能不能促消费"
  },
  {
    "url": "/weibo?q=%23Angelababy%E6%9F%93%E5%8F%91%E4%BA%86%23&t=31&band_rank=4&Refer=top",
    "title": "Angelababy染发了"
  },
  {
    "url": "/weibo?q=%23%E9%A2%86%E5%85%8BZ10%E7%9C%81%E5%BF%83%E4%BB%B7%23&t=31&band_rank=25&Refer=top",
    "title": "领克Z10省心价"
  },
  {
    "url": "/weibo?q=%23Pest%E5%8F%91%E6%AD%8Cdiss%E5%91%A8%E5%AF%86%23&t=31&band_rank=5&Refer=top",
    "title": "Pest发歌diss周密"
  },
  {
    "url": "/weibo?q=%E7%A5%9D%E7%BB%AA%E4%B8%B9%20%E5%BE%88%E5%BC%80%E5%BF%83%E9%99%AA%E4%BD%A0%E8%B5%B0%E8%BF%87%E4%B8%80%E6%AE%B5%E8%B7%AF&t=31&band_rank=27&Refer=top",
    "title": "祝绪丹 很开心陪你走过一段路"
  },
  {
    "url": "/weibo?q=%23%E8%B5%B5%E9%9C%B2%E6%80%9D%E7%9F%AD%E5%8F%91%E8%B4%9D%E9%9B%B7%E5%B8%BD%E9%80%A0%E5%9E%8B%23&t=31&band_rank=28&Refer=top",
    "title": "赵露思短发贝雷帽造型"
  },
  {
    "url": "/weibo?q=%23%E8%8B%8F%E9%86%92%E5%9B%9E%E5%BA%94%E6%AD%A6%E8%89%BA%E6%8E%A8%E8%8D%90%E4%BB%96%E5%8F%82%E5%8A%A0%E5%86%8D%E8%A7%81%E7%88%B1%E4%BA%BA%23&t=31&band_rank=29&Refer=top",
    "title": "苏醒回应武艺推荐他参加再见爱人"
  },
  {
    "url": "/weibo?q=%23%E8%B5%B5%E5%B0%8F%E7%AB%A5%E9%87%8E%E7%94%B7%E4%BA%BA%E9%82%82%E9%80%85%E9%87%8E%E7%89%9B%23&t=31&band_rank=30&Refer=top",
    "title": "赵小童野男人邂逅野牛"
  },
  {
    "url": "/weibo?q=%23%E7%94%B7%E5%AD%9039.9%E5%85%83%E7%BD%91%E8%B4%AD%E5%B9%B3%E6%9D%BF%E7%94%B5%E8%84%91%E5%88%B0%E8%B4%A7%E5%8F%98%E8%80%B3%E6%9C%BA%23&t=31&band_rank=31&Refer=top",
    "title": "男子39.9元网购平板电脑到货变耳机"
  },
  {
    "url": "/weibo?q=%23%E7%BD%91%E7%BA%A2%E5%BD%A9%E8%99%B9%E5%A4%AB%E5%A6%87%E5%A5%B3%E5%84%BF%E7%A1%AE%E8%AF%8AABO%E6%BA%B6%E8%A1%80%23&t=31&band_rank=1&Refer=top",
    "title": "网红彩虹夫妇女儿确诊ABO溶血"
  },
  {
    "url": "/weibo?q=%E9%B9%BF%E6%99%97%E7%9B%B4%E6%92%AD%E9%A2%84%E6%B5%8B&t=31&band_rank=37&Refer=top",
    "title": "鹿晗直播预测"
  },
  {
    "url": "/weibo?q=%23%E5%AF%BC%E5%B8%88%E7%9C%8B%E5%88%B0%E6%88%91%E7%9A%84%E8%AE%BA%E6%96%87%E6%9F%A5%E9%87%8D%E7%8E%87%E6%98%AF0%25%E6%97%B6%23&t=31&band_rank=34&Refer=top",
    "title": "导师看到我的论文查重率是0%时"
  },
  {
    "url": "/weibo?q=%E6%B2%A1%E4%BA%BA%E5%92%8C%E6%88%91%E8%AF%B4%E8%BF%99%E6%98%AF%E8%83%A1%E5%85%88%E7%85%A6%E5%95%8A&t=31&band_rank=35&Refer=top",
    "title": "没人和我说这是胡先煦啊"
  },
  { "url": "/weibo?q=%E4%B8%91%E8%80%81%E5%85%AC&t=31&band_rank=5&Refer=top", "title": "丑老公" },
  {
    "url": "/weibo?q=%232%E5%B2%81%E5%AD%A9%E5%AD%90%E5%B0%86%E7%94%B5%E6%B1%A0%E6%94%BE%E5%98%B4%E9%87%8C%E5%92%AC%E5%8F%91%E7%94%9F%E7%88%86%E7%82%B8%23&t=31&band_rank=28&Refer=top",
    "title": "2岁孩子将电池放嘴里咬发生爆炸"
  },
  {
    "url": "/weibo?q=%E5%85%B6%E4%BB%96rapper%E6%8F%90%E8%B5%B7%E5%91%A8%E5%AF%86%E6%AC%B2%E8%A8%80%E5%8F%88%E6%AD%A2&t=31&band_rank=18&Refer=top",
    "title": "其他rapper提起周密欲言又止"
  },
  {
    "url": "/weibo?q=%E7%9C%BC%E7%A7%91%E4%B8%93%E5%AE%B6%E6%8F%AD%E7%A7%98%E6%89%8B%E6%9C%BA%E5%B1%8F%E5%B9%95%E6%8A%A4%E7%9C%BC%E8%83%BD%E5%8A%9B%E7%9C%9F%E7%9B%B8&t=31&band_rank=39&Refer=top",
    "title": "眼科专家揭秘手机屏幕护眼能力真相"
  },
  {
    "url": "/weibo?q=%23%E9%87%91%E6%B3%B0%E4%BA%A8%E7%9A%84%E5%B0%8F%E7%8B%97%E9%87%91%E7%A2%B3%E5%8E%BB%E4%B8%96%23&t=31&band_rank=12&Refer=top",
    "title": "金泰亨的小狗金碳去世"
  },
  {
    "url": "/weibo?q=%E8%94%A1%E6%96%87%E9%9D%99%E6%96%B0%E6%B5%AA%E7%89%9B%E9%A9%AC&t=31&band_rank=41&Refer=top",
    "title": "蔡文静新浪牛马"
  },
  {
    "url": "/weibo?q=%2329%E5%90%8D%E5%BB%BA%E7%AD%91%E5%B7%A5%E8%B5%B4%E9%A6%99%E6%B8%AF%E6%89%93%E5%B7%A5%E6%9C%88%E8%96%AA3%E4%B8%87%23&t=31&band_rank=42&Refer=top",
    "title": "29名建筑工赴香港打工月薪3万"
  },
  {
    "url": "/weibo?q=%23%E9%9E%A0%E5%A9%A7%E7%A5%8E%E5%86%8D%E6%BC%94%E6%81%B6%E5%A5%B3%23&t=31&band_rank=4&Refer=top",
    "title": "鞠婧祎再演恶女"
  },
  {
    "url": "/weibo?q=%E7%BD%91%E6%98%93%E4%BA%91%E9%9F%B3%E4%B9%90%E5%B4%A9%E4%BA%86&t=31&band_rank=31&Refer=top",
    "title": "网易云音乐崩了"
  },
  {
    "url": "/weibo?q=%23%E8%8D%A3%E8%80%80300%E8%99%9A%E5%8C%96%E6%95%88%E6%9E%9C%E6%AF%94%E8%82%A9%E5%8D%95%E5%8F%8D%E7%9B%B8%E6%9C%BA%23&t=31&band_rank=45&Refer=top",
    "title": "荣耀300虚化效果比肩单反相机"
  },
  {
    "url": "/weibo?q=%E5%BC%A0%E9%A6%A8%E4%BA%88%E5%9C%A8%E8%A5%BF%E8%97%8F%E4%BD%8F%E4%B8%89%E4%B8%AA%E6%9C%88&t=31&band_rank=4&Refer=top",
    "title": "张馨予在西藏住三个月"
  },
  {
    "url": "/weibo?q=%23%E4%B8%AD%E6%96%B9%E5%9B%9E%E5%BA%94%E7%AB%8B%E9%99%B6%E5%AE%9B%E8%A6%81%E6%B1%82%E6%88%91%E5%A4%96%E4%BA%A4%E4%BA%BA%E5%91%98%E9%99%90%E6%9C%9F%E7%A6%BB%E5%A2%83%23&t=31&band_rank=5&Refer=top",
    "title": "中方回应立陶宛要求我外交人员限期离境"
  },
  {
    "url": "/weibo?q=%23%E9%9F%A9%E5%9B%BD%E6%97%85%E8%A1%8C%E7%A4%BE%E7%94%A8%E4%B8%AD%E5%9B%BD%E7%BE%8E%E9%A3%9F%E5%90%B8%E5%BC%95%E5%B9%B4%E8%BD%BB%E4%BA%BA%23&t=31&band_rank=50&Refer=top",
    "title": "韩国旅行社用中国美食吸引年轻人"
  },
  {
    "url": "/weibo?q=%23%E6%9D%AD%E5%B7%9E%E5%88%B0%E8%BE%BE%E5%A5%BD%E5%A4%9A%E6%98%8E%E6%98%9F%23&t=31&band_rank=32&Refer=top",
    "title": "杭州到达好多明星"
  },
  {
    "url": "/weibo?q=%23%E7%99%BD%E7%A3%B7%E9%80%9F%E5%BA%A6%E5%B0%B1%E6%98%AF%E5%BF%AB%23&t=31&band_rank=50&Refer=top",
    "title": "白磷速度就是快"
  },
  {
    "url": "/weibo?q=%23%E6%88%91%E5%9B%BD%E5%86%B0%E9%9B%AA%E4%BA%A7%E4%B8%9A%E8%A7%84%E6%A8%A1%E6%88%96%E5%B0%86%E7%AA%81%E7%A0%B4%E4%B8%87%E4%BA%BF%E5%85%83%23&t=31&band_rank=3&Refer=top",
    "title": "我国冰雪产业规模或将突破万亿元"
  },
  {
    "url": "/weibo?q=%23%E5%89%8D%E4%BD%93%E6%93%8D%E5%86%A0%E5%86%9B%E5%BC%A0%E5%AE%8F%E6%B6%9B%E5%9B%9E%E5%BA%94%E6%93%A6%E8%BE%B9%E4%BA%89%E8%AE%AE%23&t=31&band_rank=23&Refer=top",
    "title": "前体操冠军张宏涛回应擦边争议"
  },
  {
    "url": "/weibo?q=%23%E9%9F%A9%E5%9B%BD%E8%B5%B4%E5%8D%8E%E8%AE%A2%E5%8D%95%E6%9A%B4%E5%A2%9E%E4%B8%8A%E6%B5%B7%E6%88%90%E5%A4%A7%E7%83%AD%E9%97%A8%23&t=31&band_rank=44&Refer=top",
    "title": "韩国赴华订单暴增上海成大热门"
  },
  {
    "url": "/weibo?q=%23%E5%BC%80%E8%BD%A6%E5%89%8D%E4%B8%80%E4%B8%AA%E5%B0%8F%E5%8A%A8%E4%BD%9C%E6%88%96%E6%8C%BD%E6%95%91%E4%B8%80%E6%9D%A1%E5%B0%8F%E7%94%9F%E5%91%BD%23&t=31&band_rank=9&Refer=top",
    "title": "开车前一个小动作或挽救一条小生命"
  },
  {
    "url": "/weibo?q=%23ABO%E6%BA%B6%E8%A1%80%E7%97%87%E5%8F%8A%E6%97%B6%E5%B0%B1%E8%AF%8A%E6%B2%BB%E6%84%88%E7%8E%87100%25%23&t=31&band_rank=10&Refer=top",
    "title": "ABO溶血症及时就诊治愈率100%"
  },
  {
    "url": "/weibo?q=%23%E5%B1%B1%E4%B8%9C%E9%9D%92%E5%B2%9B%E5%8F%91%E5%B8%83%E5%A6%88%E5%A6%88%E5%B2%97%E7%94%A8%E4%BA%BA%E7%9B%AE%E5%BD%95%23&t=31&band_rank=15&Refer=top",
    "title": "山东青岛发布妈妈岗用人目录"
  },
  {
    "url": "/weibo?q=%23%E8%82%96%E6%88%98%E6%96%B9%E5%8F%96%E8%AF%81%E7%BB%B4%E6%9D%83%23&t=31&band_rank=16&Refer=top",
    "title": "肖战方取证维权"
  },
  {
    "url": "/weibo?q=%23%E4%BA%BA%E4%BA%BA%E7%BD%91%E5%B7%B2%E5%81%9C%E6%AD%A2%E6%9C%8D%E5%8A%A1%23&t=31&band_rank=15&Refer=top",
    "title": "人人网已停止服务"
  },
  {
    "url": "/weibo?q=%23%E7%99%BD%E5%A4%9C%E7%A0%B4%E6%99%93%E8%AF%84%E8%AE%BA%E5%8C%BA%E7%82%B8%E8%9A%82%E8%9A%B1%23&t=31&band_rank=18&Refer=top",
    "title": "白夜破晓评论区炸蚂蚱"
  },
  {
    "url": "/weibo?q=%23%E5%A4%B1%E6%81%8B%E4%B9%B0%E9%86%89%E5%90%8E%E8%B7%9F%E8%AD%A6%E5%AF%9F%E8%A6%81%E5%BE%AE%E4%BF%A1%23&t=31&band_rank=19&Refer=top",
    "title": "失恋买醉后跟警察要微信"
  },
  {
    "url": "/weibo?q=%23%E7%8E%8B%E6%A5%9A%E9%92%A6%E8%AF%B4%E8%90%BD%E5%90%8E%E6%98%AF%E5%9B%A0%E4%B8%BA%E5%A4%AA%E6%83%B3%E6%89%93%E5%87%BA%E6%84%9F%E8%A7%89%23&t=31&band_rank=43&Refer=top",
    "title": "王楚钦说落后是因为太想打出感觉"
  },
  {
    "url": "/weibo?q=%23%E8%B1%AA%E5%A3%AB1%E6%89%B9%E6%AC%A1%E9%9D%A2%E5%8C%85%E9%9C%89%E8%8F%8C%E8%B6%85%E6%A0%87%E8%BF%916%E5%80%8D%23&t=31&band_rank=23&Refer=top",
    "title": "豪士1批次面包霉菌超标近6倍"
  },
  {
    "url": "/weibo?q=%E8%8A%92%E6%9E%9C%E5%81%9A%E5%A3%B0%E7%94%9F%E4%B8%8D%E6%81%AF%E7%9A%84%E6%84%8F%E4%B9%89&t=31&band_rank=34&Refer=top",
    "title": "芒果做声生不息的意义"
  },
  {
    "url": "/weibo?q=%23%E5%90%B4%E6%9F%B3%E8%8A%B3%E6%9B%BE%E5%8F%82%E5%8A%A0%E5%BE%88%E5%A4%9A%E5%85%AC%E7%9B%8A%E6%94%AF%E6%95%99%E6%B4%BB%E5%8A%A8%23&t=31&band_rank=23&Refer=top",
    "title": "吴柳芳曾参加很多公益支教活动"
  },
  {
    "url": "/weibo?q=%23%E6%9E%97%E8%AF%97%E6%A0%8B%E8%92%AF%E6%9B%BC%E8%B5%A2%E4%BA%86%23&t=31&band_rank=25&Refer=top",
    "title": "林诗栋蒯曼赢了"
  },
  {
    "url": "/weibo?q=%E9%9D%92%E8%8F%9C%E7%82%92%E6%B3%A5%E8%9B%8B&t=31&band_rank=37&Refer=top",
    "title": "青菜炒泥蛋"
  },
  {
    "url": "/weibo?q=%23%E5%B0%8F%E4%BC%99%E7%9B%B8%E4%BA%B25%E5%B9%B4%E5%A8%B6%E4%BA%86%E4%B8%AA%E6%B4%8B%E5%AA%B3%E5%A6%87%23&t=31&band_rank=38&Refer=top",
    "title": "小伙相亲5年娶了个洋媳妇"
  },
  {
    "url": "/weibo?q=%23%E5%91%A8%E5%AF%86%E7%88%86%E6%96%99%E4%B8%BA%E5%91%A8%E8%8A%AF%E7%AB%B9%E6%88%90%E7%AB%8B%E7%9A%84%E5%85%AC%E5%8F%B8%E5%B7%B2%E6%B3%A8%E9%94%80%23&t=31&band_rank=8&Refer=top",
    "title": "周密爆料为周芯竹成立的公司已注销"
  },
  {
    "url": "/weibo?q=%23%E5%B9%BF%E4%B8%9C%E6%B1%9F%E9%97%A8%E6%97%A9%E8%8C%B6%E8%BE%B9%E5%90%83%E8%BE%B9%E7%9C%8BWWE%23&t=31&band_rank=30&Refer=top",
    "title": "广东江门早茶边吃边看WWE"
  },
  {
    "url": "/weibo?q=%23%E5%AE%8B%E6%85%A7%E4%B9%94%E8%A3%B4%E7%A7%80%E6%99%BA%E5%BA%86%E7%94%9F%E5%90%88%E7%85%A7%23&t=31&band_rank=11&Refer=top",
    "title": "宋慧乔裴秀智庆生合照"
  },
  {
    "url": "/weibo?q=%E5%88%9A%E8%80%83%E5%AE%8C%E5%B0%B1%E7%9F%A5%E9%81%93%E6%88%90%E7%BB%A9%E4%BA%86&t=31&band_rank=32&Refer=top",
    "title": "刚考完就知道成绩了"
  },
  {
    "url": "/weibo?q=%23%E5%AD%99%E9%A2%96%E8%8E%8E%E5%AE%89%E6%8E%92%E5%B0%8F%E5%AD%A9%E5%93%A5%E6%8D%A1%E7%90%83%23&t=31&band_rank=13&Refer=top",
    "title": "孙颖莎安排小孩哥捡球"
  },
  {
    "url": "/weibo?q=%23%E5%B0%BD%E9%87%8F%E5%88%AB%E7%94%A8%E6%89%8B%E6%9F%84%E8%BF%87%E4%BA%8E%E9%B2%9C%E8%89%B3%E7%9A%84%E8%B7%B3%E7%BB%B3%23&t=31&band_rank=47&Refer=top",
    "title": "尽量别用手柄过于鲜艳的跳绳"
  },
  {
    "url": "/weibo?q=%23%E8%B4%BA%E5%B3%BB%E9%9C%96%E9%9E%A0%E8%BA%AC%E6%84%9F%E8%B0%A2%E8%AE%A9%E8%B7%AF%E5%8F%B8%E6%9C%BA%23&t=31&band_rank=38&Refer=top",
    "title": "贺峻霖鞠躬感谢让路司机"
  },
  {
    "url": "/weibo?q=%23%E5%AD%99%E9%A2%96%E8%8E%8E%E6%97%A0%E6%B3%95%E5%AE%9E%E7%8E%B0%E7%9A%84%E5%BA%A7%E4%BD%8D%E8%87%AA%E7%94%B1%23&t=31&band_rank=45&Refer=top",
    "title": "孙颖莎无法实现的座位自由"
  },
  {
    "url": "/weibo?q=%23%E8%B6%8530%25%E5%BC%80%E9%97%A8%E6%9D%80%E4%BA%8B%E6%95%85%E5%BC%95%E5%8F%91%E4%BA%8C%E6%AC%A1%E4%BA%8B%E6%95%85%23&t=31&band_rank=9&Refer=top",
    "title": "超30%开门杀事故引发二次事故"
  },
  {
    "url": "/weibo?q=%E6%B2%A1%E4%BA%BA%E5%91%8A%E8%AF%89%E6%88%91%E7%8E%8B%E6%BA%90%E9%83%AD%E4%BF%8A%E8%BE%B0%E5%85%B3%E7%B3%BB%E8%BF%99%E4%B9%88%E5%A5%BD&t=31&band_rank=16&Refer=top",
    "title": "没人告诉我王源郭俊辰关系这么好"
  },
  {
    "url": "/weibo?q=%23%E5%8C%BB%E5%AD%A6%E5%8D%9A%E5%A3%AB%E7%A7%B0%E5%8E%8B%E5%8A%9B%E5%A4%A7%E5%88%B0%E6%9C%89%E8%BA%AF%E4%BD%93%E5%8C%96%E7%97%87%E7%8A%B6%23&t=31&band_rank=30&Refer=top",
    "title": "医学博士称压力大到有躯体化症状"
  },
  { "url": "/weibo?q=Tian%E6%99%92%E5%A5%96%E6%9D%AF&t=31&band_rank=44&Refer=top", "title": "Tian晒奖杯" },
  {
    "url": "/weibo?q=%E9%99%B7%E5%85%A5%E6%88%91%E4%BB%AC%E7%9A%84%E7%83%AD%E6%81%8B&t=31&band_rank=42&Refer=top",
    "title": "陷入我们的热恋"
  },
  {
    "url": "/weibo?q=%23%E7%94%B7%E5%AD%90%E9%80%83%E7%94%9F%E5%8F%88%E5%9B%9E%E7%81%AB%E5%9C%BA%E6%8A%A2%E6%95%91%E8%B4%A2%E7%89%A9%E9%81%87%E9%9A%BE%23&t=31&band_rank=46&Refer=top",
    "title": "男子逃生又回火场抢救财物遇难"
  },
  {
    "url": "/weibo?q=%23%E6%A2%81%E5%BB%BA%E7%AB%A0%E5%BB%BA%E8%AE%AE%E5%8F%96%E6%B6%88%E4%B8%AD%E9%AB%98%E8%80%83%23&t=31&band_rank=43&Refer=top",
    "title": "梁建章建议取消中高考"
  },
  {
    "url": "/weibo?q=%E7%99%BD%E5%A4%9C%E7%A0%B4%E6%99%93%20%E5%BF%83%E7%9C%BC%E5%AD%90%E5%8F%AA%E7%95%99%E7%BB%99%E8%87%AA%E5%B7%B1%E4%BA%BA&t=31&band_rank=48&Refer=top",
    "title": "白夜破晓 心眼子只留给自己人"
  },
  {
    "url": "/weibo?q=%23%E5%BD%A9%E8%99%B9%E5%A4%AB%E5%A6%87%E4%B8%BA%E7%94%9F%E5%A5%B3%E5%84%BF5%E5%B9%B4%E6%8B%BC4%E8%83%8E%23&t=31&band_rank=10&Refer=top",
    "title": "彩虹夫妇为生女儿5年拼4胎"
  },
  {
    "url": "/weibo?q=%23%E4%BA%BA%E5%B7%A5%E6%99%BA%E9%9A%9C%E4%BB%8D%E6%98%AF%E6%89%AB%E5%9C%B0%E6%9C%BA%E5%99%A8%E4%BA%BA%E7%9A%84%E9%80%9A%E7%97%85%23&t=31&band_rank=15&Refer=top",
    "title": "人工智障仍是扫地机器人的通病"
  },
  {
    "url": "/weibo?q=%23%E6%95%99%E8%B5%84%E9%9D%A2%E8%AF%95%E9%80%9A%E8%BF%87%E7%8E%87%E6%9C%89%E5%A4%9A%E9%AB%98%23&t=31&band_rank=34&Refer=top",
    "title": "教资面试通过率有多高"
  },
  {
    "url": "/weibo?q=%23%E7%B4%A7%E6%80%A5%E6%83%85%E5%86%B5%E4%B8%8B%E5%8F%8D%E6%9D%80%E9%BB%91%E7%86%8A%E5%8F%AF%E4%B8%8D%E6%89%BF%E6%8B%85%E6%B3%95%E5%BE%8B%E8%B4%A3%E4%BB%BB%23&t=31&band_rank=20&Refer=top",
    "title": "紧急情况下反杀黑熊可不承担法律责任"
  },
  {
    "url": "/weibo?q=%23%E6%96%87%E6%A3%AE%E7%89%B9%E9%A6%96%E5%8F%91%23&t=31&band_rank=25&Refer=top",
    "title": "文森特首发"
  },
  {
    "url": "/weibo?q=%23%E9%80%80%E5%AD%A6%E7%9A%84%E5%8D%9A%E5%A3%AB%E7%94%9F%E4%BB%AC%23&t=31&band_rank=19&Refer=top",
    "title": "退学的博士生们"
  },
  {
    "url": "/weibo?q=%E9%AA%84%E9%98%B3%E4%BC%BC%E6%88%91%E5%AE%8C%E9%A2%9C%E7%8E%B0%E5%81%B6&t=31&band_rank=27&Refer=top",
    "title": "骄阳似我完颜现偶"
  },
  {
    "url": "/weibo?q=%23%E5%BD%A9%E8%99%B9%E5%A4%AB%E5%A6%87%E5%A6%BB%E5%AD%90%E5%90%83%E5%9B%9E%E5%A5%B6%E8%8D%AF%23&t=31&band_rank=24&Refer=top",
    "title": "彩虹夫妇妻子吃回奶药"
  },
  {
    "url": "/weibo?q=%23%E5%90%B4%E6%9F%B3%E8%8A%B3%E8%AF%B4%E7%94%9F%E6%B4%BB%E8%A6%81%E9%9D%A0%E8%87%AA%E5%B7%B1%23&t=31&band_rank=29&Refer=top",
    "title": "吴柳芳说生活要靠自己"
  },
  {
    "url": "/weibo?q=%23%E9%9E%A0%E5%A9%A7%E7%A5%8E%E6%9C%88%E9%B3%9E%E7%BB%AE%E7%BA%AA%E5%87%BA%E5%A6%86%23&t=31&band_rank=7&Refer=top",
    "title": "鞠婧祎月鳞绮纪出妆"
  },
  {
    "url": "/weibo?q=%E6%B0%B8%E5%A4%9C%E6%98%9F%E6%B2%B3%E5%88%B0%E5%BA%95%E8%97%8F%E4%BA%86%E5%A4%9A%E5%B0%91%E5%A5%BD%E4%B8%9C%E8%A5%BF&t=31&band_rank=35&Refer=top",
    "title": "永夜星河到底藏了多少好东西"
  },
  {
    "url": "/weibo?q=%23%E5%94%90%E5%AB%A3%E8%AF%B4%E7%9B%AE%E5%89%8D%E6%98%AF%E4%BA%BA%E7%94%9F%E4%B8%AD%E6%9C%80%E6%94%BE%E6%9D%BE%E7%9A%84%E9%98%B6%E6%AE%B5%23&t=31&band_rank=36&Refer=top",
    "title": "唐嫣说目前是人生中最放松的阶段"
  },
  {
    "url": "/weibo?q=%E8%80%83%E5%8F%A4%E6%BD%98%E7%B2%A4%E6%98%8E&t=31&band_rank=37&Refer=top",
    "title": "考古潘粤明"
  },
  {
    "url": "/weibo?q=%23%E9%9F%A9%E5%9B%BD%E6%B5%81%E8%A1%8C%E5%91%A8%E4%BA%94%E4%B8%8B%E7%8F%AD%E5%8E%BB%E4%B8%AD%E5%9B%BD%23&t=31&band_rank=6&Refer=top",
    "title": "韩国流行周五下班去中国"
  },
  {
    "url": "/weibo?q=%23%E6%9E%97%E8%AF%97%E6%A0%8B%E7%BB%99%E7%8E%8B%E6%A5%9A%E9%92%A6%E7%9C%8B%E4%B9%92%E4%B9%92%23&t=31&band_rank=39&Refer=top",
    "title": "林诗栋给王楚钦看乒乒"
  },
  {
    "url": "/weibo?q=%23ABO%E6%BA%B6%E8%A1%80%E6%98%AF%E4%BB%80%E4%B9%88%23&t=31&band_rank=42&Refer=top",
    "title": "ABO溶血是什么"
  },
  {
    "url": "/weibo?q=%23%E9%9D%92%E8%8F%9C%E7%82%92%E6%B3%A5%E8%9B%8B%E6%B0%B8%E4%B9%85%E7%A6%81%E8%A8%80%23&t=31&band_rank=46&Refer=top",
    "title": "青菜炒泥蛋永久禁言"
  },
  {
    "url": "/weibo?q=%23%E8%99%9E%E4%B9%A6%E6%AC%A3%E4%B8%81%E7%A6%B9%E5%85%AE%E6%B5%B7%E8%BE%B9%E5%8F%8C%E4%BA%BA%E5%90%88%E7%85%A7%23&t=31&band_rank=48&Refer=top",
    "title": "虞书欣丁禹兮海边双人合照"
  },
  {
    "url": "/weibo?q=%23%E6%95%99%E8%82%B2%E5%B1%80%E4%BB%8B%E5%85%A5%E5%BA%9F%E5%BC%83%E5%B0%8F%E5%AD%A6%E4%BF%A1%E7%AE%B1%E5%8F%91%E7%8E%B0%E4%B8%BE%E6%8A%A5%E4%BF%A1%23&t=31&band_rank=21&Refer=top",
    "title": "教育局介入废弃小学信箱发现举报信"
  },
  {
    "url": "/weibo?q=%23CUBE%E5%AE%98%E5%AE%A3gidle%E7%BB%AD%E7%BA%A6%23&t=31&band_rank=30&Refer=top",
    "title": "CUBE官宣gidle续约"
  },
  {
    "url": "/weibo?q=%23%E5%85%AC%E5%AE%89%E9%83%A8%E7%BD%91%E5%AE%89%E5%B1%80%E6%8F%90%E9%86%92%E8%AD%A6%E6%83%95%E9%93%B6%E7%8B%90%E7%97%85%E6%AF%92%23&t=31&band_rank=3&Refer=top",
    "title": "公安部网安局提醒警惕银狐病毒"
  },
  {
    "url": "/weibo?q=%23%E5%8E%BF%E5%9F%8E%E5%95%86%E5%9C%88%E5%93%81%E7%89%8C%E9%83%BD%E6%98%AF%E5%A4%8D%E5%88%B6%E7%B2%98%E8%B4%B4%23&t=31&band_rank=10&Refer=top",
    "title": "县城商圈品牌都是复制粘贴"
  },
  {
    "url": "/weibo?q=%23%E6%B8%85%E5%8D%8E%E5%A4%A7%E5%AD%A6%E9%80%9A%E6%8A%A5%E4%B8%80%E5%AD%A6%E7%94%9F%E5%9C%A8%E5%A4%96%E6%A0%A1%E4%B8%8E%E4%BA%BA%E5%86%B2%E7%AA%81%23&t=31&band_rank=14&Refer=top",
    "title": "清华大学通报一学生在外校与人冲突"
  },
  {
    "url": "/weibo?q=%23%E8%B4%B5%E5%B7%9E%E5%8F%91%E7%94%9F%E4%B8%80%E8%B5%B7%E7%BF%BB%E8%88%B9%E4%BA%8B%E6%95%85%E8%87%B48%E4%BA%BA%E6%AD%BB%E4%BA%A1%23&t=31&band_rank=19&Refer=top",
    "title": "贵州发生一起翻船事故致8人死亡"
  },
  {
    "url": "/weibo?q=%23%E8%8D%AF%E7%8E%8B%E8%B0%B7%E6%8A%97%E7%99%8C%E4%B8%AD%E5%BF%83%E9%83%A8%E5%88%86%E5%8C%BB%E6%8A%A4%E6%97%A0%E8%B5%84%E8%B4%A8%23&t=31&band_rank=20&Refer=top",
    "title": "药王谷抗癌中心部分医护无资质"
  },
  {
    "url": "/weibo?q=%23%E7%94%B7%E5%AD%90%E8%87%AA%E7%A7%B0%E7%83%9F%E8%8D%89%E5%B1%80%E4%B8%BB%E7%AE%A1%E5%AE%89%E6%8E%92%E5%85%A5%E8%81%8C%E9%9C%80%E9%99%AA%E7%9D%A1%23&t=31&band_rank=23&Refer=top",
    "title": "男子自称烟草局主管安排入职需陪睡"
  },
  {
    "url": "/weibo?q=%23%E7%94%B0%E5%98%89%E7%91%9E%E6%9C%88%E9%B3%9E%E7%BB%AE%E7%BA%AA%E5%BC%80%E6%9C%BA%E5%87%BA%E5%A6%86%E8%B7%AF%E9%80%8F%23&t=31&band_rank=22&Refer=top",
    "title": "田嘉瑞月鳞绮纪开机出妆路透"
  },
  {
    "url": "/weibo?q=%23%E6%9D%A8%E5%B9%82%E7%9A%84%E4%BA%AB%E7%95%8CS9%E6%80%8E%E4%B9%88%E5%BC%80%E9%83%BD%E6%9C%89%E9%9D%A2%23&t=31&band_rank=23&Refer=top",
    "title": "杨幂的享界S9怎么开都有面"
  },
  {
    "url": "/weibo?q=%E7%8E%8B%E6%A5%9A%E9%92%A6%E5%A4%AA%E5%8F%AF%E7%88%B1%E4%BA%86&t=31&band_rank=27&Refer=top",
    "title": "王楚钦太可爱了"
  },
  {
    "url": "/weibo?q=%23%E6%9C%AA%E5%AE%9A%E4%BA%8B%E4%BB%B6%E7%B0%BF%23&t=31&band_rank=29&Refer=top",
    "title": "未定事件簿"
  },
  {
    "url": "/weibo?q=%E9%99%88%E6%A2%A6%E9%87%8D%E8%BF%94%E8%AE%AD%E7%BB%83%E5%9C%BA%E8%A7%86%E9%A2%91%E6%9B%9D%E5%85%89&t=31&band_rank=28&Refer=top",
    "title": "陈梦重返训练场视频曝光"
  },
  {
    "url": "/weibo?q=%23%E7%94%B7%E5%AD%90%E5%90%91%E5%88%AB%E5%9B%BD%E6%8F%90%E4%BE%9B%E6%88%91%E5%9B%BD%E5%AE%B6%E7%A7%98%E5%AF%86%E6%8D%A2%E7%BB%BF%E5%8D%A1%23&t=31&band_rank=26&Refer=top",
    "title": "男子向别国提供我国家秘密换绿卡"
  },
  {
    "url": "/weibo?q=%23%E6%9D%8E%E8%A0%95%E8%A0%95%E6%A8%A1%E4%BB%BF%E9%BA%A6%E7%90%B3%23&t=31&band_rank=32&Refer=top",
    "title": "李蠕蠕模仿麦琳"
  },
  {
    "url": "/weibo?q=%23%E7%A7%A6%E5%BD%BB%E6%97%A5%E5%8D%A1%E5%8F%8C%E7%99%BB%E9%A1%B6%23&t=31&band_rank=36&Refer=top",
    "title": "秦彻日卡双登顶"
  },
  {
    "url": "/weibo?q=%23%E7%8E%8B%E4%B8%80%E5%8D%9A%E6%97%81%E8%A7%82%E8%80%85%E5%85%A5%E5%9B%B4%E4%BA%9A%E6%B4%B2%E6%B5%81%E8%A1%8C%E9%9F%B3%E4%B9%90%E5%A4%A7%E5%A5%96%23&t=31&band_rank=37&Refer=top",
    "title": "王一博旁观者入围亚洲流行音乐大奖"
  },
  {
    "url": "/weibo?q=%23%E5%90%B4%E6%9F%B3%E8%8A%B3%E4%B8%BA%E4%BD%95%E8%A2%AB%E6%99%AE%E9%81%8D%E6%94%AF%E6%8C%81%23&t=31&band_rank=8&Refer=top",
    "title": "吴柳芳为何被普遍支持"
  },
  {
    "url": "/weibo?q=%23%E5%8F%B8%E6%9C%BA%E4%BD%9C%E5%BC%8A%E6%AC%BA%E9%AA%97%E6%99%BA%E9%A9%BE%E7%B3%BB%E7%BB%9F%E5%9C%A8%E9%AB%98%E9%80%9F%E7%9D%A1%E8%A7%89%23&t=31&band_rank=39&Refer=top",
    "title": "司机作弊欺骗智驾系统在高速睡觉"
  },
  {
    "url": "/weibo?q=%E5%A4%A9%E4%BB%B7%E4%BF%9D%E5%81%A5%E5%93%81%E6%98%AF%E6%80%8E%E4%B9%88%E5%BF%BD%E6%82%A0%E4%BD%8F%E7%88%B8%E5%A6%88%E7%9A%84&t=31&band_rank=40&Refer=top",
    "title": "天价保健品是怎么忽悠住爸妈的"
  },
  {
    "url": "/weibo?q=%23%E8%B1%AA%E5%A3%AB%E5%9B%9E%E5%BA%94%E9%9D%A2%E5%8C%85%E9%9C%89%E8%8F%8C%E8%B6%85%E6%A0%87%E8%BF%916%E5%80%8D%23&t=31&band_rank=41&Refer=top",
    "title": "豪士回应面包霉菌超标近6倍"
  },
  {
    "url": "/weibo?q=%E6%81%8B%E4%B8%8E%E6%B7%B1%E7%A9%BA%E7%99%BB%E9%A1%B6&t=31&band_rank=22&Refer=top",
    "title": "恋与深空登顶"
  },
  { "url": "/weibo?q=%E6%81%8B%E4%B8%8E%E6%B7%B1%E7%A9%BA&t=31&band_rank=25&Refer=top", "title": "恋与深空" },
  {
    "url": "/weibo?q=%23%E7%8E%8B%E6%A5%9A%E9%92%A6%E5%AD%99%E9%A2%96%E8%8E%8E%E5%87%BB%E6%8E%8C%E5%BA%86%E7%A5%9D%23&t=31&band_rank=11&Refer=top",
    "title": "王楚钦孙颖莎击掌庆祝"
  },
  {
    "url": "/weibo?q=%23%E5%90%8D%E4%B8%8B%E5%85%B3%E8%81%94%E4%BA%86%E5%A4%9A%E5%B0%91%E8%B4%A6%E5%8F%B7%E5%8F%AF%E9%80%9F%E6%9F%A5%23&t=31&band_rank=47&Refer=top",
    "title": "名下关联了多少账号可速查"
  },
  {
    "url": "/weibo?q=%E5%B0%8F%E7%8C%AB%E6%96%9C%E6%8C%8E%E5%8C%85&t=31&band_rank=50&Refer=top",
    "title": "小猫斜挎包"
  },
  {
    "url": "/weibo?q=%23%E5%85%B1%E5%BB%BA%E4%B8%80%E5%B8%A6%E4%B8%80%E8%B7%AF%E6%B3%A8%E9%87%8D%E7%9A%84%E6%98%AF%E4%BC%97%E4%BA%BA%E6%8B%BE%E6%9F%B4%E7%81%AB%E7%84%B0%E9%AB%98%23&Refer=new_time",
    "title": "共建一带一路注重的是众人拾柴火焰高"
  },
  {
    "url": "/weibo?q=%23%E5%A5%B3%E5%AD%908%E5%B0%8F%E6%97%B6%E4%B8%8D%E7%8E%A9%E6%89%8B%E6%9C%BA%E8%B5%A2%E5%BE%97%E4%B8%87%E5%85%83%E5%A5%96%E9%87%91%23&t=31&band_rank=1&Refer=top",
    "title": "女子8小时不玩手机赢得万元奖金"
  },
  {
    "url": "/weibo?q=%23%E8%AF%BB%E6%87%82%E6%94%B9%E9%9D%A9%E5%A5%8B%E8%BF%9B%E7%9A%84%E4%B8%AD%E5%9B%BD%23&t=31&band_rank=3&Refer=top",
    "title": "读懂改革奋进的中国"
  },
  {
    "url": "/weibo?q=%23%E4%B8%AD%E5%9B%BD%E5%B0%8F%E5%8C%BA%E4%B8%BA%E4%BD%95%E5%AE%B9%E6%98%93%E5%8F%98%E6%88%90%E8%80%81%E7%A0%B4%E5%B0%8F%23&t=31&band_rank=10&Refer=top",
    "title": "中国小区为何容易变成老破小"
  },
  {
    "url": "/weibo?q=%E5%90%B4%E6%9F%B3%E8%8A%B3%E6%9B%BE%E8%AF%B4%E6%83%B3%E8%87%AA%E5%B7%B1%E6%B2%89%E6%B7%80&t=31&band_rank=14&Refer=top",
    "title": "吴柳芳曾说想自己沉淀"
  },
  {
    "url": "/weibo?q=%23%E5%9B%BD%E4%B9%92%E5%9B%9E%E5%BA%94%E6%88%98%E8%83%9C%E5%8D%B0%E5%BA%A6%E9%98%9F%23&t=31&band_rank=10&Refer=top",
    "title": "国乒回应战胜印度队"
  },
  {
    "url": "/weibo?q=%E5%86%AF%E7%BB%8D%E5%B3%B0%E7%9B%B4%E6%92%AD%E5%9B%9E%E5%AE%B6%E7%9A%84%E8%AF%B1%E6%83%91&t=31&band_rank=17&Refer=top",
    "title": "冯绍峰直播回家的诱惑"
  },
  {
    "url": "/weibo?q=%23%E7%BD%91%E4%BC%A0%E5%9B%BD%E8%B6%B3%E5%86%B2%E5%9C%BA%E7%90%83%E8%BF%B7%E5%8F%91%E6%96%87%E5%9B%9E%E5%BA%94%23&t=31&band_rank=18&Refer=top",
    "title": "网传国足冲场球迷发文回应"
  },
  {
    "url": "/weibo?q=%23%E5%8E%9F%E7%A5%9E%E5%92%96%E5%95%A1%E7%88%86%E5%8D%95%23&t=31&band_rank=20&Refer=top",
    "title": "原神咖啡爆单"
  },
  {
    "url": "/weibo?q=%23%E6%B2%88%E6%A2%A6%E8%BE%B0%E7%8E%8B%E6%98%9F%E8%B6%8A%E5%90%88%E7%85%A7%23&t=31&band_rank=24&Refer=top",
    "title": "沈梦辰王星越合照"
  },
  {
    "url": "/weibo?q=%23%E6%9B%9D%E9%BA%A6%E7%90%B3%E7%96%91%E4%BC%BC%E7%AD%BE%E5%85%AC%E5%8F%B8%23&t=31&band_rank=27&Refer=top",
    "title": "曝麦琳疑似签公司"
  },
  {
    "url": "/weibo?q=%23%E9%83%91%E5%B0%91%E7%A7%8B%E8%B5%B5%E9%9B%85%E8%8A%9D%E5%90%8C%E6%A1%86%23&t=31&band_rank=29&Refer=top",
    "title": "郑少秋赵雅芝同框"
  },
  {
    "url": "/weibo?q=%23KPL%E5%B9%B4%E6%80%BB%E7%BE%A4%E5%83%8F%E7%BA%AA%E5%BD%95%E7%89%87%23&t=31&band_rank=31&Refer=top",
    "title": "KPL年总群像纪录片"
  },
  {
    "url": "/weibo?q=%23%E8%8D%AF%E7%8E%8B%E8%B0%B7%E5%BC%80%E8%AF%8A1%E4%B8%AA%E5%A4%9A%E6%9C%8815%E5%90%8D%E6%82%A3%E8%80%85%E6%AD%BB%E4%BA%A1%23&t=31&band_rank=1&Refer=top",
    "title": "药王谷开诊1个多月15名患者死亡"
  },
  {
    "url": "/weibo?q=%23%E6%9D%8E%E4%B8%80%E6%A1%90%E5%90%AC%E5%88%B0%E6%80%80%E5%AD%95%E5%B8%A6%E7%90%83%E8%B7%91%E7%9A%84%E5%8F%8D%E5%BA%94%23&t=31&band_rank=33&Refer=top",
    "title": "李一桐听到怀孕带球跑的反应"
  },
  {
    "url": "/weibo?q=%23%E9%BA%A6%E5%BD%93%E5%8A%B3%E4%B8%8B%E8%B0%83%E9%85%8D%E9%80%81%E8%B4%B9%E6%94%B6%E5%8F%96%E6%89%93%E5%8C%85%E8%B4%B9%23&t=31&band_rank=5&Refer=top",
    "title": "麦当劳下调配送费收取打包费"
  },
  {
    "url": "/weibo?q=%E7%8E%B0%E5%9C%A8%E5%B0%B1%E5%87%BA%E5%8F%91%E9%80%81%E7%A6%8F%E5%88%A9&t=31&band_rank=36&Refer=top",
    "title": "现在就出发送福利"
  },
  {
    "url": "/weibo?q=%23%E5%AE%B6%E9%95%BF%E5%90%90%E6%A7%BD%E5%B9%BC%E5%84%BF%E5%9B%AD%E8%B0%83%E6%9F%A5%E9%97%AE%E5%8D%B7%E9%97%AE%E9%A2%98%E7%A6%BB%E8%B0%B1%23&t=31&band_rank=39&Refer=top",
    "title": "家长吐槽幼儿园调查问卷问题离谱"
  },
  {
    "url": "/weibo?q=%E5%91%A8%E8%8A%AF%E7%AB%B9%20%E5%91%A8%E5%AF%86&t=31&band_rank=16&Refer=top",
    "title": "周芯竹 周密"
  },
  {
    "url": "/weibo?q=%23%E9%99%A2%E5%A3%AB%E8%AF%B4%E7%8E%B0%E5%9C%A8%E4%B8%80%E9%A1%BF%E9%A5%AD%E7%9A%84%E7%83%AD%E9%87%8F%E5%A4%AA%E9%AB%98%23&t=31&band_rank=24&Refer=top",
    "title": "院士说现在一顿饭的热量太高"
  },
  {
    "url": "/weibo?q=%23%E5%BD%A9%E8%99%B9%E5%A4%AB%E5%A6%87%E5%9B%9E%E5%BA%94%E5%A5%B3%E5%84%BF%E7%A1%AE%E8%AF%8AABO%E6%BA%B6%E8%A1%80%23&t=31&band_rank=43&Refer=top",
    "title": "彩虹夫妇回应女儿确诊ABO溶血"
  },
  { "url": "/weibo?q=%23%E4%B8%9E%E7%A3%8A%E5%8A%A9%E7%90%86%23&t=31&band_rank=5&Refer=top", "title": "丞磊助理" },
  {
    "url": "/weibo?q=%E5%AD%99%E9%A2%96%E8%8E%8E%E5%96%9D%E6%B0%B4&t=31&band_rank=43&Refer=top",
    "title": "孙颖莎喝水"
  },
  {
    "url": "/weibo?q=%2365%E4%B8%87%E6%8B%8E%E5%8C%85%E5%85%A5%E4%BD%8F%E4%B8%8A%E6%B5%B7181%E5%B9%B3%E7%B2%BE%E8%A3%85%E6%88%BF%E6%98%AF%E7%9C%9F%E7%9A%84%E5%90%97%23&t=31&band_rank=50&Refer=top",
    "title": "65万拎包入住上海181平精装房是真的吗"
  },
  {
    "url": "/weibo?q=%23%E9%9F%A9%E5%9B%BD%E5%B9%B4%E8%BD%BB%E4%BA%BA%E6%B6%8C%E5%90%91%E4%B8%AD%E5%9B%BD%E8%BF%87%E5%91%A8%E6%9C%AB%23&t=31&band_rank=43&Refer=top",
    "title": "韩国年轻人涌向中国过周末"
  },
  {
    "url": "/weibo?q=%23%E4%B8%80%E7%9C%81%E5%BE%81%E9%9B%86%E5%9B%A0%E5%A9%9A%E8%87%B4%E8%B4%AB%E6%A1%88%E4%BE%8B%23&t=31&band_rank=48&Refer=top",
    "title": "一省征集因婚致贫案例"
  },
  {
    "url": "/weibo?q=%23%E5%B7%9D%E8%88%AA%E4%B8%80%E8%88%AA%E7%8F%AD%E5%9B%A0%E6%97%85%E5%AE%A2%E5%85%85%E7%94%B5%E5%AE%9D%E5%86%92%E7%83%9F%E5%A4%87%E9%99%8D%23&t=31&band_rank=36&Refer=top",
    "title": "川航一航班因旅客充电宝冒烟备降"
  },
  {
    "url": "/weibo?q=%23%E7%8E%8B%E4%B8%80%E5%8D%9A%E7%8E%B0%E8%BA%AB%E9%A6%99%E5%A5%88%E5%84%BF%E9%AB%98%E7%BA%A7%E6%89%8B%E5%B7%A5%E5%9D%8A%23&t=31&band_rank=29&Refer=top",
    "title": "王一博现身香奈儿高级手工坊"
  },
  {
    "url": "/weibo?q=%E8%94%A1%E6%96%87%E9%9D%99%E9%97%AE%E5%86%AF%E7%BB%8D%E5%B3%B0%E6%80%8E%E4%B9%88%E6%92%95%E6%B8%A3%E7%94%B7&t=31&band_rank=14&Refer=top",
    "title": "蔡文静问冯绍峰怎么撕渣男"
  },
  {
    "url": "/weibo?q=%23%E7%BA%AA%E5%A7%94%E7%AA%81%E5%87%BB%E6%A3%80%E6%9F%A5%E5%B7%A5%E4%BD%9C%E4%BA%BA%E5%91%98%E7%BB%8F%E5%82%AC%E4%BF%83%E6%89%8D%E5%88%B0%E5%B2%97%23&t=31&band_rank=15&Refer=top",
    "title": "纪委突击检查工作人员经催促才到岗"
  },
  {
    "url": "/weibo?q=%E6%97%A5%E6%9C%AC%E6%BC%94%E5%91%98%E5%A4%B8%E4%BD%A0%E5%A5%BD%E6%9D%8E%E7%84%95%E8%8B%B1%E6%98%AF%E5%A5%BD%E7%94%B5%E5%BD%B1&t=31&band_rank=19&Refer=top",
    "title": "日本演员夸你好李焕英是好电影"
  },
  {
    "url": "/weibo?q=%23%E5%A4%9A%E5%9C%B0%E5%87%BA%E7%8E%B0%E6%AE%8B%E7%96%BE%E4%BA%BA%E8%A1%A8%E6%BC%94%E5%9B%A2%E8%BF%9B%E5%B0%8F%E5%8C%BA%E8%AF%88%E9%AA%97%23&t=31&band_rank=20&Refer=top",
    "title": "多地出现残疾人表演团进小区诈骗"
  },
  {
    "url": "/weibo?q=%E5%B7%B3%E5%8D%87%E5%8D%87%E6%98%A5%E6%99%9A%E5%90%89%E7%A5%A5%E7%89%A9&t=31&band_rank=21&Refer=top",
    "title": "巳升升春晚吉祥物"
  },
  {
    "url": "/weibo?q=%23%E6%97%B6%E7%A9%BA%E4%B8%AD%E7%9A%84%E7%BB%98%E6%97%85%E4%BA%BA%23&t=31&band_rank=25&Refer=top",
    "title": "时空中的绘旅人"
  },
  {
    "url": "/weibo?q=%23%E6%95%99%E8%82%B2%E5%B1%80%E5%9B%9E%E5%BA%94%E8%80%81%E5%B8%88%E8%A2%AB%E5%A4%9A%E5%90%8D%E5%B0%8F%E5%AD%A6%E7%94%9F%E5%86%99%E4%BF%A1%E6%8A%95%E8%AF%89%23&t=31&band_rank=8&Refer=top",
    "title": "教育局回应老师被多名小学生写信投诉"
  },
  {
    "url": "/weibo?q=%E9%A6%99%E5%A5%88%E5%84%BF%E6%89%8B%E5%B7%A5%E5%9D%8A%E5%A4%A7%E7%A7%80%E9%80%89%E5%9D%80%E8%A5%BF%E6%B9%96&t=31&band_rank=27&Refer=top",
    "title": "香奈儿手工坊大秀选址西湖"
  },
  {
    "url": "/weibo?q=%23%E5%AE%8B%E4%BA%9A%E8%BD%A9%E8%87%AA%E6%9B%9D%E4%BD%93%E9%87%8D%23&t=31&band_rank=12&Refer=top",
    "title": "宋亚轩自曝体重"
  },
  {
    "url": "/weibo?q=%E5%BC%A0%E5%B0%8F%E6%96%90%E8%A6%81%E5%92%96%E5%95%A1800%E4%B8%AA%E5%81%87%E5%8A%A8%E4%BD%9C&t=31&band_rank=29&Refer=top",
    "title": "张小斐要咖啡800个假动作"
  },
  {
    "url": "/weibo?q=%E5%96%9C%E5%89%A7%E4%B9%8B%E7%8E%8B%E5%BC%80%E6%9C%BA&t=31&band_rank=16&Refer=top",
    "title": "喜剧之王开机"
  },
  {
    "url": "/weibo?q=%23%E9%9E%A0%E5%A9%A7%E7%A5%8E%E9%99%88%E9%83%BD%E7%81%B5%E6%9C%88%E9%B3%9E%E7%BB%AE%E7%BA%AA%E9%80%86%E5%BA%94%E6%8F%B4%23&t=31&band_rank=42&Refer=top",
    "title": "鞠婧祎陈都灵月鳞绮纪逆应援"
  },
  {
    "url": "/weibo?q=%23%E9%BA%A6%E7%90%B3%E6%9C%AA%E5%9C%A8%E6%9D%8E%E8%A1%8C%E4%BA%AE%E7%BB%8F%E7%BA%AA%E5%85%AC%E5%8F%B8%E6%8C%81%E8%82%A1%23&t=31&band_rank=17&Refer=top",
    "title": "麦琳未在李行亮经纪公司持股"
  },
  {
    "url": "/weibo?q=%23%E4%B8%81%E7%A6%B9%E5%85%AE%E5%85%89%E9%80%9F%E4%B8%8B%E7%BA%BF%23&t=31&band_rank=35&Refer=top",
    "title": "丁禹兮光速下线"
  },
  {
    "url": "/weibo?q=%23%E6%B3%B0%E5%9B%BD%E5%9D%A0%E5%B4%96%E5%AD%95%E5%A6%87%E4%B8%8E%E7%AE%A1%E6%99%A8%E8%BE%B0%E7%AD%BE%E7%BA%A6%E5%90%8C%E5%AE%B6MCN%23&t=31&band_rank=35&Refer=top",
    "title": "泰国坠崖孕妇与管晨辰签约同家MCN"
  },
  {
    "url": "/weibo?q=%23%E5%90%B4%E6%9F%B3%E8%8A%B3%E6%97%A9%E5%B9%B4%E9%80%89%E6%8B%94%E8%B5%9B%E5%8F%97%E4%BC%A4%E8%A7%86%E9%A2%91%E6%B5%81%E5%87%BA%23&t=31&band_rank=39&Refer=top",
    "title": "吴柳芳早年选拔赛受伤视频流出"
  },
  {
    "url": "/weibo?q=%E5%8D%81%E4%BA%8C%E6%9C%88%E7%9A%84%E5%A5%87%E8%BF%B9&t=31&band_rank=35&Refer=top",
    "title": "十二月的奇迹"
  },
  {
    "url": "/weibo?q=%23%E7%A0%94%E7%A9%B6%E8%AF%81%E6%98%8E%E6%9C%89%E9%A5%A5%E9%A5%BF%E6%84%9F%E4%BC%9A%E5%90%AF%E5%8A%A8%E9%95%BF%E5%AF%BF%E5%9F%BA%E5%9B%A0%23&t=31&band_rank=33&Refer=top",
    "title": "研究证明有饥饿感会启动长寿基因"
  },
  {
    "url": "/weibo?q=%23%E7%94%B7%E5%AD%90%E7%BD%91%E6%81%8B%E8%A2%AB%E9%AA%97%E5%8F%88%E6%89%AE%E5%A5%B3%E6%80%A7%E9%AA%97%E5%8F%A6%E4%B8%80%E7%94%B7%E5%AD%90%23&t=31&band_rank=9&Refer=top",
    "title": "男子网恋被骗又扮女性骗另一男子"
  },
  {
    "url": "/weibo?q=%23%E8%9B%87%E5%B9%B4%E6%98%A5%E6%99%9A%E5%90%89%E7%A5%A5%E7%89%A9%E7%A6%8F%E4%BB%8E%E5%A4%B4%E8%B5%B7%E5%B0%BE%E9%9A%8F%E5%A6%82%E6%84%8F%23&t=31&band_rank=44&Refer=top",
    "title": "蛇年春晚吉祥物福从头起尾随如意"
  },
  {
    "url": "/weibo?q=%23%E6%AD%A6%E8%89%BA%E6%8E%A8%E8%8D%90%E8%8B%8F%E9%86%92%E5%8F%82%E5%8A%A0%E5%86%8D%E8%A7%81%E7%88%B1%E4%BA%BA%23&t=31&band_rank=10&Refer=top",
    "title": "武艺推荐苏醒参加再见爱人"
  },
  {
    "url": "/weibo?q=%23%E5%A0%B5%E8%BD%A6%E6%97%B6%E9%97%AF%E7%BB%BF%E7%81%AF%E5%B1%9E%E8%BF%9D%E6%B3%95%E8%A1%8C%E4%B8%BA%23&t=31&band_rank=1&Refer=top",
    "title": "堵车时闯绿灯属违法行为"
  },
  {
    "url": "/weibo?q=%23%E8%99%9E%E4%B9%A6%E6%AC%A3%E9%97%AE%E4%B8%81%E7%A6%B9%E5%85%AE%E6%8B%BC%E8%B1%86%E5%91%A2%23&t=31&band_rank=34&Refer=top",
    "title": "虞书欣问丁禹兮拼豆呢"
  },
  {
    "url": "/weibo?q=%23%E7%9B%97%E7%89%88%E9%BA%A6%E7%90%B3%E6%9D%A8%E5%AD%90%E8%BF%9E%E9%BA%A6%23&t=31&band_rank=48&Refer=top",
    "title": "盗版麦琳杨子连麦"
  },
  {
    "url": "/weibo?q=%23%E6%99%8B%E6%B1%9F%E4%B8%80%E4%B8%AA%E5%8E%BF%E7%BA%A7%E5%B8%82%E4%B8%BA%E4%BB%80%E4%B9%88%E7%9B%9B%E4%BA%A7%E5%A4%A7%E5%85%AC%E5%8F%B8%23&t=31&band_rank=49&Refer=top",
    "title": "晋江一个县级市为什么盛产大公司"
  },
  {
    "url": "/weibo?q=%23%E7%AE%A1%E6%99%A8%E8%BE%B0%E5%BE%AE%E5%8D%9A%E9%81%AD%E5%A4%A7%E9%87%8F%E6%89%B9%E8%AF%84%E6%94%BB%E5%87%BB%23&t=31&band_rank=4&Refer=top",
    "title": "管晨辰微博遭大量批评攻击"
  },
  {
    "url": "/weibo?q=%23%E7%AE%A1%E6%99%A8%E8%BE%B0%E5%B7%B2%E5%81%9C%E6%9B%B42%E5%91%A8%23&t=31&band_rank=14&Refer=top",
    "title": "管晨辰已停更2周"
  },
  {
    "url": "/weibo?q=%23%E5%8C%BB%E4%BF%9D%E8%B7%A8%E7%9C%81%E7%9B%B4%E6%8E%A5%E7%BB%93%E7%AE%97%E6%96%B0%E5%A2%9E5%E7%A7%8D%E9%97%A8%E8%AF%8A%E6%85%A2%E7%89%B9%E7%97%85%23&t=31&band_rank=15&Refer=top",
    "title": "医保跨省直接结算新增5种门诊慢特病"
  },
  {
    "url": "/weibo?q=%23%E5%BC%A0%E8%89%BA%E8%B0%8B%E4%B8%80%E5%AE%B6%E5%8F%82%E5%8A%A0%E5%B7%B4%E9%BB%8E%E5%90%8D%E5%AA%9B%E8%88%9E%E4%BC%9A%23&t=31&band_rank=17&Refer=top",
    "title": "张艺谋一家参加巴黎名媛舞会"
  },
  {
    "url": "/weibo?q=%23%E5%B8%82%E7%9B%91%E5%B1%80%E5%9B%9E%E5%BA%94%E6%80%9D%E5%BF%B5%E6%B0%B4%E9%A5%BA%E7%96%91%E5%90%83%E5%87%BA%E7%83%9F%E5%A4%B4%23&t=31&band_rank=18&Refer=top",
    "title": "市监局回应思念水饺疑吃出烟头"
  },
  {
    "url": "/weibo?q=%23%E5%91%A8%E5%AF%86%E4%B8%8E%E5%91%A8%E8%8A%AF%E7%AB%B9%E6%97%A0%E8%82%A1%E6%9D%83%E5%85%B3%E8%81%94%23&t=31&band_rank=19&Refer=top",
    "title": "周密与周芯竹无股权关联"
  },
  {
    "url": "/weibo?q=%23OBGG%E6%98%BE%E7%A4%BAXiaohao%E5%8A%A0%E5%85%A5EDG%23&t=31&band_rank=20&Refer=top",
    "title": "OBGG显示Xiaohao加入EDG"
  },
  { "url": "/weibo?q=%E5%91%A8%E5%A4%BA%E7%AC%8B&t=31&band_rank=31&Refer=top", "title": "周夺笋" },
  {
    "url": "/weibo?q=%232025%E6%B1%9F%E8%8B%8F%E5%8D%AB%E8%A7%86%E8%B7%A8%E5%B9%B4%E6%BC%94%E5%94%B1%E4%BC%9A%E5%AE%98%E5%AE%A3%23&t=31&band_rank=26&Refer=top",
    "title": "2025江苏卫视跨年演唱会官宣"
  },
  {
    "url": "/weibo?q=%23%E8%BF%99%E6%9C%9F%E6%AF%9B%E9%9B%AA%E6%B1%AA%E4%BF%A1%E6%81%AF%E9%87%8F%E5%A5%BD%E5%A4%A7%23&t=31&band_rank=27&Refer=top",
    "title": "这期毛雪汪信息量好大"
  },
  {
    "url": "/weibo?q=%E7%8E%8B%E6%A5%9A%E9%92%A6vs%E8%8B%8F%E6%8B%89%E7%93%A6%E6%9C%B1%E6%8B%89&t=31&band_rank=11&Refer=top",
    "title": "王楚钦vs苏拉瓦朱拉"
  },
  {
    "url": "/weibo?q=%23%E5%93%88%E7%99%BB%E7%94%9F%E6%B6%AF3000%E8%AE%B0%E4%B8%89%E5%88%86%23&t=31&band_rank=30&Refer=top",
    "title": "哈登生涯3000记三分"
  },
  {
    "url": "/weibo?q=%23%E9%87%91%E9%AB%98%E9%93%B6%E6%9D%A5%E6%9D%AD%E5%B7%9E%E4%BA%86%23&t=31&band_rank=7&Refer=top",
    "title": "金高银来杭州了"
  },
  {
    "url": "/weibo?q=%23%E6%B3%B0%E5%9B%BD%E5%9D%A0%E5%B4%96%E5%AD%95%E5%A6%8711%E6%9C%88%E7%9B%B4%E6%92%AD14%E5%9C%BA%23&t=31&band_rank=28&Refer=top",
    "title": "泰国坠崖孕妇11月直播14场"
  },
  {
    "url": "/weibo?q=%23%E5%AD%99%E9%A2%96%E8%8E%8E%E8%A7%82%E6%88%98%23&t=31&band_rank=16&Refer=top",
    "title": "孙颖莎观战"
  },
  { "url": "/weibo?q=%23%E6%8E%98%E9%87%91vs%E5%BF%AB%E8%88%B9%23&t=31&band_rank=40&Refer=top", "title": "掘金vs快船" },
  {
    "url": "/weibo?q=%23%E4%BB%85%E6%9C%8939.6%E4%B8%87%E4%BA%BA%E6%94%BE%E5%BC%83%E5%9B%BD%E8%80%83%23&t=31&band_rank=40&Refer=top",
    "title": "仅有39.6万人放弃国考"
  },
  { "url": "/weibo?q=%E7%8C%8E%E7%BD%AA%E5%9B%BE%E9%89%B4&t=31&band_rank=8&Refer=top", "title": "猎罪图鉴" },
  {
    "url": "/weibo?q=%23%E8%83%83%E7%97%85%E5%8F%98%E8%83%83%E7%99%8C%E5%89%8D%E4%B8%80%E8%88%AC%E6%9C%895%E4%B8%AA%E7%97%87%E7%8A%B6%23&t=31&band_rank=22&Refer=top",
    "title": "胃病变胃癌前一般有5个症状"
  },
  {
    "url": "/weibo?q=%23iG%E5%AE%98%E5%AE%A3%E6%96%B0%E9%98%B5%E5%AE%B9%E5%89%AA%E5%BD%B1%23&t=31&band_rank=38&Refer=top",
    "title": "iG官宣新阵容剪影"
  },
  {
    "url": "/weibo?q=%23%E6%B7%B7%E5%9B%A2%E5%9B%BD%E4%B9%92%E4%BC%98%E5%8A%BF%E5%A4%AA%E6%98%8E%E6%98%BE%23&t=31&band_rank=47&Refer=top",
    "title": "混团国乒优势太明显"
  },
  {
    "url": "/weibo?q=%23%E6%AD%A6%E8%89%BA%E8%AF%B4%E5%86%8D%E8%A7%81%E7%88%B1%E4%BA%BA%E6%B2%A1%E5%89%A7%E6%9C%AC%23&t=31&band_rank=48&Refer=top",
    "title": "武艺说再见爱人没剧本"
  },
  {
    "url": "/weibo?q=%E5%88%98%E6%B5%A9%E5%AD%98%E9%AB%98%E9%A9%AC%E5%B0%BE&t=31&band_rank=49&Refer=top",
    "title": "刘浩存高马尾"
  },
  {
    "url": "/weibo?q=%23%E5%B7%9D%E8%88%AA%E5%9B%9E%E5%BA%943U8925%E8%88%AA%E7%8F%AD%E5%A4%87%E9%99%8D%E6%A1%82%E6%9E%97%23&t=31&band_rank=10&Refer=top",
    "title": "川航回应3U8925航班备降桂林"
  },
  {
    "url": "/weibo?q=%23%E5%8D%97%E6%9E%81%E4%B8%AD%E5%B1%B1%E5%9B%BD%E5%AE%B6%E5%A4%A7%E6%B0%94%E6%9C%AC%E5%BA%95%E7%9B%91%E6%B5%8B%E7%AB%99%E5%BB%BA%E6%88%90%23&t=31&band_rank=3&Refer=top",
    "title": "南极中山国家大气本底监测站建成"
  },
  {
    "url": "/weibo?q=%23%E7%BD%91%E5%8F%8B%E5%9C%A8%E5%B0%8F%E5%AD%A6%E5%BA%9F%E5%BC%83%E4%BF%A1%E7%AE%B1%E5%8F%91%E7%8E%B0%E5%A4%9A%E5%B0%81%E6%8A%95%E8%AF%89%E4%BF%A1%23&t=31&band_rank=33&Refer=top",
    "title": "网友在小学废弃信箱发现多封投诉信"
  },
  {
    "url": "/weibo?q=%23%E5%A7%9C%E4%BA%91%E5%8D%87%E8%B0%88%E9%99%88%E8%BF%91%E5%8D%97diss%E5%91%A8%E5%AF%86%23&t=31&band_rank=7&Refer=top",
    "title": "姜云升谈陈近南diss周密"
  },
  {
    "url": "/weibo?q=%23%E4%B8%8A%E6%B5%B7%E6%B7%B1%E5%9C%B311%E6%9C%88%E4%BA%8C%E6%89%8B%E6%88%BF%E6%88%90%E4%BA%A4%E9%87%8F%E9%BD%90%E5%88%9B%E6%96%B0%E9%AB%98%23&t=31&band_rank=14&Refer=top",
    "title": "上海深圳11月二手房成交量齐创新高"
  },
  {
    "url": "/weibo?q=%23%E9%9E%A0%E5%A9%A7%E7%A5%8E%E5%AF%B9%E8%9C%9C%E6%A9%98%E4%BB%AC%E7%9A%84%E7%88%B1%23&t=31&band_rank=18&Refer=top",
    "title": "鞠婧祎对蜜橘们的爱"
  },
  {
    "url": "/weibo?q=%23%E7%BD%97%E4%BA%91%E7%86%99%E4%B8%BA%E9%A2%9C%E5%BF%83%E8%AE%B0%E6%89%93call%23&t=31&band_rank=19&Refer=top",
    "title": "罗云熙为颜心记打call"
  },
  {
    "url": "/weibo?q=%23%E7%8E%8B%E6%9B%BC%E6%98%B1%E7%90%83%E5%93%81%E5%A5%BD%E4%BA%BA%E5%93%81%E5%A5%BD%23&t=31&band_rank=20&Refer=top",
    "title": "王曼昱球品好人品好"
  },
  {
    "url": "/weibo?q=%E5%88%98%E6%B5%A9%E5%AD%98%E6%8E%8C%E7%AE%A1%E9%AB%98%E9%A9%AC%E5%B0%BE%E7%9A%84%E7%A5%9E&t=31&band_rank=11&Refer=top",
    "title": "刘浩存掌管高马尾的神"
  },
  {
    "url": "/weibo?q=%23%E9%AA%84%E9%98%B3%E4%BC%BC%E6%88%91%E5%AE%98%E5%AE%A3%E8%B5%B5%E4%BB%8A%E9%BA%A6%E5%AE%8B%E5%A8%81%E9%BE%99%23&t=31&band_rank=32&Refer=top",
    "title": "骄阳似我官宣赵今麦宋威龙"
  },
  {
    "url": "/weibo?q=%E5%91%A8%E8%8A%AF%E7%AB%B9%20%E9%AB%98%E5%A4%A9%E4%BD%90&t=31&band_rank=5&Refer=top",
    "title": "周芯竹 高天佐"
  },
  {
    "url": "/weibo?q=%E5%BC%A0%E5%B0%8F%E6%96%90%E7%B2%89%E4%B8%9D%20%E5%A7%90%E5%A7%90%E6%88%91%E6%98%AF%E4%BD%A0%E7%9A%84%E7%8B%97&t=31&band_rank=27&Refer=top",
    "title": "张小斐粉丝 姐姐我是你的狗"
  },
  {
    "url": "/weibo?q=%23%E6%91%87%E5%85%89%E5%BD%95%E4%B9%B1%E4%B8%96%E5%85%AC%E4%B8%BB%E5%81%9C%E6%AD%A2%E6%9B%B4%E6%96%B0%23&t=31&band_rank=29&Refer=top",
    "title": "摇光录乱世公主停止更新"
  },
  {
    "url": "/weibo?q=%23%E5%AE%8B%E4%BA%9A%E8%BD%A9%E7%99%BD%E6%9C%88%E5%85%89vs%E6%9C%B1%E7%A0%82%E7%97%A3%23&t=31&band_rank=30&Refer=top",
    "title": "宋亚轩白月光vs朱砂痣"
  },
  {
    "url": "/weibo?q=%E8%B4%BE%E7%8E%B2%E6%92%91%E8%85%B0%E5%BC%A0%E5%B0%8F%E6%96%90%E6%96%B0%E5%89%A7&t=31&band_rank=32&Refer=top",
    "title": "贾玲撑腰张小斐新剧"
  },
  {
    "url": "/weibo?q=%23%E6%B3%B0%E5%9B%BD%E5%9D%A0%E5%B4%96%E5%AD%95%E5%A6%87%E8%A2%AB%E6%8C%87%E8%B4%A3%E7%94%9F%E6%84%8F%E5%81%9A%E5%A4%AA%E5%A4%A7%23&t=31&band_rank=1&Refer=top",
    "title": "泰国坠崖孕妇被指责生意做太大"
  },
  {
    "url": "/weibo?q=%23%E8%99%9E%E4%B9%A6%E6%AC%A3%E4%B8%81%E7%A6%B9%E5%85%AE%E5%B9%95%E5%90%8E%E6%89%93%E9%97%B9%23&t=31&band_rank=36&Refer=top",
    "title": "虞书欣丁禹兮幕后打闹"
  },
  {
    "url": "/weibo?q=%E5%AE%8B%E5%A8%81%E9%BE%99%E6%97%B6%E9%9A%94%E5%9B%9B%E5%B9%B4%E5%86%8D%E6%BC%94%E7%8E%B0%E5%81%B6&t=31&band_rank=38&Refer=top",
    "title": "宋威龙时隔四年再演现偶"
  },
  {
    "url": "/weibo?q=%E9%BB%91%E7%99%BD%E6%A3%AE%E6%9E%97%E5%AE%9A%E6%A1%A3&t=31&band_rank=8&Refer=top",
    "title": "黑白森林定档"
  },
  {
    "url": "/weibo?q=%23%E6%9D%8E%E8%A1%8C%E4%BA%AE12%E6%9C%88%E8%87%B3%E5%B0%91%E6%9C%892%E4%B8%AA%E6%BC%94%E5%87%BA%E8%AE%A1%E5%88%92%23&t=31&band_rank=2&Refer=top",
    "title": "李行亮12月至少有2个演出计划"
  },
  {
    "url": "/weibo?q=%23%E6%B2%A1%E6%83%B3%E5%88%B0%E5%90%83%E5%89%A9%E7%9A%84%E9%AA%A8%E5%A4%B4%E8%BF%98%E8%83%BD%E8%BF%99%E6%A0%B7%E7%94%A8%23&t=31&band_rank=44&Refer=top",
    "title": "没想到吃剩的骨头还能这样用"
  },
  {
    "url": "/weibo?q=%E5%AD%9F%E5%AD%90%E4%B9%89%E9%A6%96%E6%BC%94%E9%87%8D%E7%94%9F%E5%A4%8D%E4%BB%87%E5%A4%A7%E5%A5%B3%E4%B8%BB&t=31&band_rank=46&Refer=top",
    "title": "孟子义首演重生复仇大女主"
  },
  {
    "url": "/weibo?q=%23%E4%B8%81%E7%A6%B9%E5%85%AE%E4%BB%8A%E5%B9%B4%E7%AC%AC%E5%9B%9B%E9%83%A8%E5%89%A7%23&t=31&band_rank=34&Refer=top",
    "title": "丁禹兮今年第四部剧"
  },
  {
    "url": "/weibo?q=aespa%20%E6%98%9F%E9%99%85%E5%A5%B3%E6%88%98%E5%A3%ABwinter&t=31&band_rank=45&Refer=top",
    "title": "aespa 星际女战士winter"
  },
  {
    "url": "/weibo?q=%E4%BD%9F%E5%A4%A7%E4%B8%BA%E8%8A%B1%E6%9C%9F%E7%9C%9F%E9%95%BF&t=31&band_rank=30&Refer=top",
    "title": "佟大为花期真长"
  },
  {
    "url": "/weibo?q=%E5%A4%8F%E4%B9%8B%E5%85%89%20%E5%85%89%E5%A4%B4%E9%80%A0%E5%9E%8B&t=31&band_rank=49&Refer=top",
    "title": "夏之光 光头造型"
  },
  {
    "url": "/weibo?q=%23iG%E6%96%B0%E9%98%B5%E5%AE%B9%E5%B0%86%E5%9C%A8%E4%BC%A0%E5%A5%87%E6%9D%AF%E5%86%B3%E8%B5%9B%E7%8E%B0%E5%9C%BA%E5%85%AC%E5%B8%83%23&t=31&band_rank=35&Refer=top",
    "title": "iG新阵容将在传奇杯决赛现场公布"
  },
  {
    "url": "/weibo?q=%23%E4%B8%AD%E5%8D%8E%E6%B0%91%E6%97%8F%E6%98%AF%E5%AE%88%E6%AD%A3%E5%88%9B%E6%96%B0%E7%9A%84%E6%B0%91%E6%97%8F%23&Refer=new_time",
    "title": "中华民族是守正创新的民族"
  },
  {
    "url": "/weibo?q=%23%E8%85%BE%E8%AE%AF12%E6%9C%88%E5%A4%A7%E5%89%A7%E7%89%87%E5%8D%95%23&t=31&band_rank=12&Refer=top",
    "title": "腾讯12月大剧片单"
  },
  {
    "url": "/weibo?q=%23%E4%BB%8A%E5%B9%B4%E4%B9%8C%E5%86%9B%E9%80%83%E5%85%B5%E4%BA%BA%E6%95%B0%E5%B7%B2%E8%B6%85%E5%89%8D%E4%B8%A4%E5%B9%B4%E4%B9%8B%E5%92%8C%23&t=31&band_rank=15&Refer=top",
    "title": "今年乌军逃兵人数已超前两年之和"
  },
  {
    "url": "/weibo?q=%E7%BA%A2%E7%B3%96%E6%B0%B4%E6%B2%A1%E7%94%A8%20%E5%BE%97%E5%90%83%E5%8E%BB%E7%97%9B%E7%89%87&t=31&band_rank=16&Refer=top",
    "title": "红糖水没用 得吃去痛片"
  },
  {
    "url": "/weibo?q=%23A%E8%82%A1%E4%B8%89%E5%A4%A7%E6%8C%87%E6%95%B0%E5%9D%87%E6%B6%A8%E9%80%BE1%25%23&t=31&band_rank=17&Refer=top",
    "title": "A股三大指数均涨逾1%"
  },
  {
    "url": "/weibo?q=%23%E6%9E%97%E8%AF%97%E6%A0%8B%E8%92%AF%E6%9B%BCVS%E9%92%B1%E5%BE%B7%E6%8B%89%E7%93%A6%E6%8F%90%E5%85%8B%23&t=31&band_rank=18&Refer=top",
    "title": "林诗栋蒯曼VS钱德拉瓦提克"
  },
  {
    "url": "/weibo?q=%23%E5%9B%B4%E8%A7%82%E6%98%8E%E6%98%9F%E5%A9%9A%E5%A7%BB%E7%9A%84%E8%A7%82%E4%BC%97%E6%88%90%E6%B5%81%E9%87%8F%E5%8F%98%E7%8E%B0%E5%B7%A5%E5%85%B7%23&t=31&band_rank=19&Refer=top",
    "title": "围观明星婚姻的观众成流量变现工具"
  },
  {
    "url": "/weibo?q=%23%E9%AB%98%E9%92%A7%E8%B4%A4%E7%BB%93%E5%A9%9A%E5%BD%93%E7%88%B8%23&t=31&band_rank=20&Refer=top",
    "title": "高钧贤结婚当爸"
  },
  {
    "url": "/weibo?q=%23%E5%8D%95%E9%9C%81%E7%BF%94%E4%B8%BA%E4%BF%9D%E6%8A%A4%E6%95%85%E5%AE%AB%E5%9C%B0%E9%9D%A2%E5%9D%9A%E6%8C%81%E7%A9%BF%E5%B8%83%E9%9E%8B%23&t=31&band_rank=9&Refer=top",
    "title": "单霁翔为保护故宫地面坚持穿布鞋"
  },
  {
    "url": "/weibo?q=%23%E5%86%AC%E6%97%A5%E6%99%BA%E9%A9%BE%E8%BF%BD%E9%9B%AAbuff%E5%8F%A0%E6%BB%A1%23&t=31&band_rank=23&Refer=top",
    "title": "冬日智驾追雪buff叠满"
  },
  { "url": "/weibo?q=%23%E5%9B%BD%E4%B9%92vs%E5%8D%B0%E5%BA%A6%23&t=31&band_rank=24&Refer=top", "title": "国乒vs印度" },
  { "url": "/weibo?q=%E6%91%87%E5%85%89%E5%BD%95&t=31&band_rank=25&Refer=top", "title": "摇光录" },
  {
    "url": "/weibo?q=%23%E6%9C%89%E4%BA%9Brapper%E4%B8%8D%E8%AF%A5%E6%8A%8A%E4%BD%8E%E4%BF%97%E5%BD%93%E4%BD%9C%E9%A3%8E%E6%A0%BC%23&t=31&band_rank=7&Refer=top",
    "title": "有些rapper不该把低俗当作风格"
  },
  {
    "url": "/weibo?q=%23%E9%A6%99%E5%A5%88%E5%84%BF%E6%9D%AD%E5%B7%9E%E5%85%A8%E7%90%83%E9%A6%96%E7%A7%80%23&t=31&band_rank=28&Refer=top",
    "title": "香奈儿杭州全球首秀"
  },
  {
    "url": "/weibo?q=%2390%E5%90%8E%E5%A5%B3%E6%8A%A4%E5%A3%AB%E5%B0%86%E6%88%BF%E9%97%B4%E4%BD%8F%E5%8C%85%E6%B5%86%E5%90%8E%E5%A4%B1%E8%81%94%23&t=31&band_rank=2&Refer=top",
    "title": "90后女护士将房间住包浆后失联"
  },
  {
    "url": "/weibo?q=%23%E8%B5%B5%E4%B8%BD%E9%A2%96%E5%A5%B3%E5%8F%8B%E8%A7%86%E8%A7%92%E6%8A%A5%E5%A4%87%E6%97%A5%E5%B8%B8%23&t=31&band_rank=32&Refer=top",
    "title": "赵丽颖女友视角报备日常"
  },
  {
    "url": "/weibo?q=%23%E9%99%88%E8%BF%91%E5%8D%97diss%E5%91%A8%E5%AF%86%23&t=31&band_rank=21&Refer=top",
    "title": "陈近南diss周密"
  },
  { "url": "/weibo?q=%E4%B9%9D%E9%87%8D%E7%B4%AB%E5%AE%9A%E6%A1%A3&t=31&band_rank=2&Refer=top", "title": "九重紫定档" },
  {
    "url": "/weibo?q=%23%E5%9B%A0%E7%A9%B7%E5%86%99%E7%BD%91%E6%96%87%E5%86%99%E6%88%90%E8%8C%85%E7%9B%BE%E5%A5%96%23&t=31&band_rank=41&Refer=top",
    "title": "因穷写网文写成茅盾奖"
  },
  {
    "url": "/weibo?q=%23%E5%AD%A6%E4%BF%A1%E7%BD%91%E5%8F%91%E4%BA%86%E6%B0%B8%E5%A4%9C%E6%98%9F%E6%B2%B3%23&t=31&band_rank=5&Refer=top",
    "title": "学信网发了永夜星河"
  },
  {
    "url": "/weibo?q=%234%E7%A7%8D%E4%BD%93%E8%B4%A8%E7%9A%84%E5%A5%B3%E6%80%A7%E6%98%93%E6%82%A3%E5%A4%9A%E5%9B%8A%23&t=31&band_rank=43&Refer=top",
    "title": "4种体质的女性易患多囊"
  },
  {
    "url": "/weibo?q=%23%E9%99%88%E9%83%BD%E7%81%B5%E6%9C%88%E9%B3%9E%E7%BB%AE%E7%BA%AA%E5%87%BA%E5%A6%86%E8%B7%AF%E9%80%8F%23&t=31&band_rank=23&Refer=top",
    "title": "陈都灵月鳞绮纪出妆路透"
  },
  {
    "url": "/weibo?q=%E5%AE%89%E5%AE%A4%E9%80%8F%E7%9F%A5%E9%81%93%E6%9F%AF%E5%8D%97%E8%BA%AB%E4%BB%BD&t=31&band_rank=17&Refer=top",
    "title": "安室透知道柯南身份"
  },
  {
    "url": "/weibo?q=%E5%A5%B3%E5%A8%B2%E5%BE%88%E5%8F%AF%E8%83%BD%E6%98%AF%E7%9C%9F%E5%AE%9E%E5%AD%98%E5%9C%A8%E8%BF%87%E7%9A%84%E4%B8%80%E7%BE%A4%E5%A5%B3%E4%BA%BA&t=31&band_rank=6&Refer=top",
    "title": "女娲很可能是真实存在过的一群女人"
  },
  {
    "url": "/weibo?q=%E5%9B%BD%E6%BC%AB%E5%92%8C%E6%97%A5%E6%BC%AB%E6%8A%95%E7%A5%A8%E5%8D%B7%E8%B5%B7%E6%9D%A5%E4%BA%86&t=31&band_rank=49&Refer=top",
    "title": "国漫和日漫投票卷起来了"
  },
  {
    "url": "/weibo?q=%E7%94%B5%E8%A7%86%E5%89%A7%E5%A4%A7%E8%B5%8F&t=31&band_rank=50&Refer=top",
    "title": "电视剧大赏"
  },
  {
    "url": "/weibo?q=%23%E8%BF%99%E6%A0%B7%E7%9A%84%E6%96%87%E7%89%A9%E6%88%8F%E7%B2%BE%E4%BA%AE%E4%BA%86%23&t=31&band_rank=3&Refer=top",
    "title": "这样的文物戏精亮了"
  },
  {
    "url": "/weibo?q=%23%E6%8B%9C%E7%99%BB%E5%84%BF%E5%AD%90%E5%9B%9E%E5%BA%94%E8%A2%AB%E5%AE%A3%E5%B8%83%E8%B5%A6%E5%85%8D%23&t=31&band_rank=11&Refer=top",
    "title": "拜登儿子回应被宣布赦免"
  },
  { "url": "/weibo?q=%E9%AA%84%E9%98%B3%E4%BC%BC%E6%88%91&t=31&band_rank=12&Refer=top", "title": "骄阳似我" },
  {
    "url": "/weibo?q=%23%E7%9C%8B%E4%BC%BC%E6%AD%A3%E5%B8%B8%E5%AE%9E%E5%88%99%E4%BC%A4%E7%89%99%E7%9A%84%E8%A1%8C%E4%B8%BA%23&t=31&band_rank=15&Refer=top",
    "title": "看似正常实则伤牙的行为"
  },
  {
    "url": "/weibo?q=%23%E7%89%B9%E6%9C%97%E6%99%AE%E5%8F%88%E6%8F%90%E5%90%8D%E4%BA%86%E4%B8%80%E4%BD%8D%E4%BA%B2%E5%AE%B6%23&t=31&band_rank=19&Refer=top",
    "title": "特朗普又提名了一位亲家"
  },
  {
    "url": "/weibo?q=%23%E5%8D%87%E7%BA%A7%E7%BA%AF%E8%A1%80%E9%B8%BF%E8%92%99%E7%9A%84%E7%90%86%E7%94%B1%E5%8F%88%E5%A4%9A%E4%BA%86%E4%B8%80%E4%B8%AA%23&t=31&band_rank=20&Refer=top",
    "title": "升级纯血鸿蒙的理由又多了一个"
  },
  {
    "url": "/weibo?q=%23IU%E8%BE%B9%E4%BD%91%E9%94%A1%E6%96%B0%E5%89%A7%23&t=31&band_rank=22&Refer=top",
    "title": "IU边佑锡新剧"
  },
  {
    "url": "/weibo?q=%23%E8%B5%B5%E4%B8%BD%E9%A2%96%E6%AD%A4%E5%88%BB%E4%B8%8E%E6%88%91%E4%BB%AC%E6%89%93%E7%85%A7%E9%9D%A2%23&t=31&band_rank=24&Refer=top",
    "title": "赵丽颖此刻与我们打照面"
  },
  {
    "url": "/weibo?q=%23%E5%9B%9B%E5%A4%A7%E6%89%9B%E5%89%A7%E5%A5%B3%E6%BC%94%E5%91%98%23&t=31&band_rank=22&Refer=top",
    "title": "四大扛剧女演员"
  },
  {
    "url": "/weibo?q=%23%E5%8D%96%E9%B1%BC%E5%93%A5%E6%94%BE%E5%BC%83%E6%BB%A1%E8%BD%A6%E9%B1%BC%E8%99%BE%E6%B3%BC1%E5%90%A8%E6%B0%B4%E6%95%91%E4%BA%BA%23&t=31&band_rank=9&Refer=top",
    "title": "卖鱼哥放弃满车鱼虾泼1吨水救人"
  },
  {
    "url": "/weibo?q=%23%E5%AE%8B%E5%A8%81%E9%BE%99%E8%B5%B5%E4%BB%8A%E9%BA%A6%E6%8C%89%E5%A7%93%E6%B0%8F%E9%A6%96%E5%AD%97%E6%AF%8D%E6%8E%92%E5%BA%8F%23&t=31&band_rank=27&Refer=top",
    "title": "宋威龙赵今麦按姓氏首字母排序"
  },
  {
    "url": "/weibo?q=%23%E5%82%85%E9%A6%96%E5%B0%94%E5%9B%9E%E5%BA%94%E7%A4%BE%E4%BA%A4%E8%B4%A6%E5%8F%B7%E5%87%A0%E4%B9%8E%E5%81%9C%E6%9B%B4%23&t=31&band_rank=29&Refer=top",
    "title": "傅首尔回应社交账号几乎停更"
  },
  {
    "url": "/weibo?q=%23%E5%90%B4%E6%9F%B3%E8%8A%B3%E7%B2%89%E4%B8%9D%E6%95%B0%E7%AA%81%E7%A0%B4400%E4%B8%87%23&t=31&band_rank=30&Refer=top",
    "title": "吴柳芳粉丝数突破400万"
  },
  {
    "url": "/weibo?q=%23%E4%BA%AC%E5%9F%8E%E5%A4%A7%E5%B8%88%E8%B5%9B%23&t=31&band_rank=31&Refer=top",
    "title": "京城大师赛"
  },
  {
    "url": "/weibo?q=%23%E5%89%8D%E4%BD%93%E6%93%8D%E8%BF%90%E5%8A%A8%E5%91%98%E5%88%98%E7%92%87%E7%96%91%E4%BC%BC%E5%BD%B1%E5%B0%84%E5%90%B4%E6%9F%B3%E8%8A%B3%23&t=31&band_rank=33&Refer=top",
    "title": "前体操运动员刘璇疑似影射吴柳芳"
  },
  {
    "url": "/weibo?q=%23%E6%9B%BE%E8%88%9C%E6%99%9E%E6%9C%88%E9%B3%9E%E7%BB%AE%E7%BA%AA%E5%BC%80%E6%9C%BA%E5%87%BA%E5%A6%86%E8%B7%AF%E9%80%8F%23&t=31&band_rank=34&Refer=top",
    "title": "曾舜晞月鳞绮纪开机出妆路透"
  },
  { "url": "/weibo?q=%E7%A7%A6%E5%BD%BB&t=31&band_rank=35&Refer=top", "title": "秦彻" },
  { "url": "/weibo?q=%E5%A5%BD%E4%B8%9C%E8%A5%BF&t=31&band_rank=36&Refer=top", "title": "好东西" },
  {
    "url": "/weibo?q=%23%E5%90%91%E6%9C%AA%E6%88%90%E5%B9%B4%E4%BA%BA%E9%94%80%E5%94%AE%E7%83%9F%E5%8D%A1%E8%BF%9D%E6%B3%95%23&t=31&band_rank=33&Refer=top",
    "title": "向未成年人销售烟卡违法"
  },
  {
    "url": "/weibo?q=%E5%A7%9C%E4%BA%91%E5%8D%87%E7%9B%B4%E6%92%AD&t=31&band_rank=38&Refer=top",
    "title": "姜云升直播"
  },
  {
    "url": "/weibo?q=%23%E6%9B%9D%E7%A7%A6%E9%9C%84%E8%B4%A4%E6%98%A5%E8%8A%82%E5%90%8E%E5%A4%8D%E5%87%BA%23&t=31&band_rank=39&Refer=top",
    "title": "曝秦霄贤春节后复出"
  },
  { "url": "/weibo?q=%E5%89%91%E7%BD%913&t=31&band_rank=40&Refer=top", "title": "剑网3" },
  {
    "url": "/weibo?q=%23%E5%8C%97%E4%BA%AC%E5%9C%B0%E9%93%81%E5%A4%A7%E7%88%B7%E5%90%91%E5%B9%B4%E8%BD%BB%E4%BA%BA%E8%8A%B1%E5%BC%8F%E5%8F%91%E5%B0%84%E5%BF%AB%E4%B9%90%23&t=31&band_rank=41&Refer=top",
    "title": "北京地铁大爷向年轻人花式发射快乐"
  },
  {
    "url": "/weibo?q=%23%E7%88%B6%E6%AF%8D%E4%B8%BA%E5%95%A5%E9%9D%9E%E8%A6%81%E6%B2%A1%E8%8B%A6%E7%A1%AC%E5%90%83%23&t=31&band_rank=42&Refer=top",
    "title": "父母为啥非要没苦硬吃"
  },
  {
    "url": "/weibo?q=%23%E5%BC%80%E5%A5%97%E7%89%8C%E8%BD%A6%E6%89%93%E4%BA%BA%E5%89%AF%E9%95%87%E9%95%BF%E5%93%AA%E6%9D%A5%E7%9A%84%E5%9A%A3%E5%BC%A0%E5%BA%95%E6%B0%94%23&t=31&band_rank=43&Refer=top",
    "title": "开套牌车打人副镇长哪来的嚣张底气"
  },
  {
    "url": "/weibo?q=%E5%AE%8B%E4%BA%9A%E8%BD%A9%E6%96%B0%E6%AD%8C%E4%BD%93%E8%B4%B4%E4%B8%8A%E7%BA%BF&t=31&band_rank=45&Refer=top",
    "title": "宋亚轩新歌体贴上线"
  },
  {
    "url": "/weibo?q=%2329%E5%B2%81%E5%85%A8%E7%9B%B2%E5%A5%B3%E7%94%9F%E8%80%83%E4%B8%8A%E5%8D%9A%E5%A3%AB%E5%90%8E%E7%9A%84%E7%94%9F%E6%B4%BB%23&t=31&band_rank=46&Refer=top",
    "title": "29岁全盲女生考上博士后的生活"
  },
  {
    "url": "/weibo?q=%23%E9%AA%84%E9%98%B3%E4%BC%BC%E6%88%91%E6%9A%96%E9%98%B3%E5%88%9D%E8%A7%81%E6%B5%B7%E6%8A%A5%23&t=31&band_rank=47&Refer=top",
    "title": "骄阳似我暖阳初见海报"
  },
  { "url": "/weibo?q=%E6%9C%88%E9%B3%9E%E7%BB%AE%E7%BA%AA&t=31&band_rank=46&Refer=top", "title": "月鳞绮纪" },
  {
    "url": "/weibo?q=%232024%E8%BF%98%E5%89%A9%E6%9C%80%E5%90%8E30%E5%A4%A9%23&t=31&band_rank=49&Refer=top",
    "title": "2024还剩最后30天"
  },
  {
    "url": "/weibo?q=%23%E5%A4%A7%E7%88%B7%E5%93%AA%E5%A4%A9%E5%87%BA%E7%8E%B0%E5%93%AA%E5%A4%A9%E5%B0%B1%E6%98%AF%E5%BF%AB%E4%B9%90%E6%98%9F%E6%9C%9F%E5%87%A0%23&t=31&band_rank=13&Refer=top",
    "title": "大爷哪天出现哪天就是快乐星期几"
  },
  {
    "url": "/weibo?q=%23%E6%8B%9C%E7%99%BB%E5%AE%A3%E5%B8%83%E8%B5%A6%E5%85%8D%E5%85%B6%E5%AD%90%23&t=31&band_rank=1&Refer=top",
    "title": "拜登宣布赦免其子"
  },
  {
    "url": "/weibo?q=%23%E8%BF%99%E4%BA%9B%E9%A3%9F%E7%89%A9%E6%98%AF%E7%BB%93%E8%8A%82%E7%9A%84%E5%82%AC%E5%8C%96%E5%89%82%23&t=31&band_rank=8&Refer=top",
    "title": "这些食物是结节的催化剂"
  },
  {
    "url": "/weibo?q=%23%E9%A6%99%E6%B8%AF3%E6%AD%B9%E5%BE%92%E5%85%A5%E5%BA%97%E6%8A%A2%E8%B5%B066%E4%B8%AA%E7%88%B1%E9%A9%AC%E4%BB%95%E5%8C%85%23&t=31&band_rank=9&Refer=top",
    "title": "香港3歹徒入店抢走66个爱马仕包"
  },
  {
    "url": "/weibo?q=%23%E8%BF%99%E6%A0%B7%E4%BD%BF%E7%94%A8%E9%81%BF%E5%AD%95%E5%A5%97%E6%98%AF%E6%97%A0%E6%95%88%E6%93%8D%E4%BD%9C%23&t=31&band_rank=11&Refer=top",
    "title": "这样使用避孕套是无效操作"
  },
  {
    "url": "/weibo?q=%23%E8%85%BE%E8%AE%AF%E5%9B%9E%E5%BA%94%E5%BE%AE%E4%BF%A1%E6%8F%90%E7%8E%B0%E5%8F%AF%E5%85%8D%E6%89%8B%E7%BB%AD%E8%B4%B9%23&t=31&band_rank=2&Refer=top",
    "title": "腾讯回应微信提现可免手续费"
  },
  {
    "url": "/weibo?q=%23%E5%82%85%E9%A6%96%E5%B0%94%E5%9B%9E%E5%BA%94%E5%82%85%E9%A6%96%E5%B0%94%E9%9D%A2%E7%9B%B8%23&t=31&band_rank=5&Refer=top",
    "title": "傅首尔回应傅首尔面相"
  },
  {
    "url": "/weibo?q=%23%E9%87%8D%E5%BA%86%E6%A3%92%E6%A3%92%E7%88%B6%E5%AD%9014%E5%B9%B4%E5%90%8E%E9%87%8D%E8%BF%94%E6%95%85%E5%9C%B0%23&t=31&band_rank=15&Refer=top",
    "title": "重庆棒棒父子14年后重返故地"
  },
  {
    "url": "/weibo?q=%23%E5%8D%8A%E5%A4%9C%E5%A4%A9%E8%8A%B1%E6%9D%BF%E4%B8%8A%E6%8E%89%E4%B8%8B%E4%B8%80%E5%8F%AA300%E6%96%A4%E9%87%8E%E7%8C%AA%23&t=31&band_rank=20&Refer=top",
    "title": "半夜天花板上掉下一只300斤野猪"
  },
  {
    "url": "/weibo?q=%23%E6%92%9E%E6%AD%BB%E7%9F%A5%E5%90%8D%E5%8C%BB%E7%94%9F%E8%82%87%E4%BA%8B%E8%80%85%E5%AE%B6%E5%B1%9E%E8%AF%B7%E6%B1%82%E8%B0%85%E8%A7%A3%23&t=31&band_rank=6&Refer=top",
    "title": "撞死知名医生肇事者家属请求谅解"
  },
  {
    "url": "/weibo?q=%23%E4%BD%95%E6%B5%A9%E6%A5%A0%E6%B2%BF%E7%9D%80%E5%85%89%E6%96%B9%E5%90%91%E5%87%BA%E5%8F%91%23&t=31&band_rank=19&Refer=top",
    "title": "何浩楠沿着光方向出发"
  },
  {
    "url": "/weibo?q=%E8%B0%81%E6%89%8D%E6%98%AF%E7%8E%B0%E5%9C%A8%E7%9A%84%E5%8A%A8%E6%BC%AB%E9%A1%B6%E6%B5%81&t=31&band_rank=20&Refer=top",
    "title": "谁才是现在的动漫顶流"
  },
  {
    "url": "/weibo?q=%E6%88%91%E6%98%AF%E5%88%91%E8%AD%A6%E9%A9%B3%E5%9B%9E%E4%BA%86%E5%8F%97%E5%AE%B3%E8%80%85%E6%9C%89%E7%BD%AA%E8%AE%BA&t=31&band_rank=23&Refer=top",
    "title": "我是刑警驳回了受害者有罪论"
  },
  {
    "url": "/weibo?q=%23%E5%AD%A9%E5%AD%90%E5%85%9C%E9%87%8C%E6%8F%A3%E9%BE%99%E7%9C%BC%E5%AE%B6%E9%95%BF%E8%B4%A8%E7%96%91%E8%B6%85%E5%B8%82%E5%AE%9A%E6%80%A7%E5%81%B7%E7%9B%97%23&t=31&band_rank=24&Refer=top",
    "title": "孩子兜里揣龙眼家长质疑超市定性偷盗"
  },
  {
    "url": "/weibo?q=%23%E5%82%85%E9%A6%96%E5%B0%94%E8%B0%88%E5%86%8D%E8%A7%81%E7%88%B1%E4%BA%BA%E5%90%8E%E7%9A%84%E7%8A%B6%E6%80%81%23&t=31&band_rank=26&Refer=top",
    "title": "傅首尔谈再见爱人后的状态"
  },
  {
    "url": "/weibo?q=%23%E5%A5%B3%E5%AD%9010%E4%BB%B6%E6%97%A7%E7%BE%BD%E7%BB%92%E6%9C%8D%E7%88%86%E6%94%B91%E5%BA%8A%E7%BE%BD%E7%BB%92%E8%A2%AB%23&t=31&band_rank=21&Refer=top",
    "title": "女子10件旧羽绒服爆改1床羽绒被"
  },
  {
    "url": "/weibo?q=%23%E5%A4%AE%E8%A7%86%E6%9B%9D%E5%85%89%E5%AD%A6%E7%94%9F%E4%BD%93%E8%82%B2%E7%94%A8%E5%93%81%E4%B8%AD%E7%9A%84%E5%A2%9E%E5%A1%91%E5%89%82%23&t=31&band_rank=10&Refer=top",
    "title": "央视曝光学生体育用品中的增塑剂"
  },
  {
    "url": "/weibo?q=%23GFriend%E9%87%8D%E7%BB%84%E5%9B%9E%E5%BD%92%23&t=31&band_rank=29&Refer=top",
    "title": "GFriend重组回归"
  },
  {
    "url": "/weibo?q=%23%E9%A2%9C%E5%A6%82%E6%99%B6%E7%98%A6%E4%BA%8655%E6%96%A4%E8%A7%A3%E9%94%81%E5%85%A8%E6%96%B0%E9%A3%8E%E6%A0%BC%23&t=31&band_rank=24&Refer=top",
    "title": "颜如晶瘦了55斤解锁全新风格"
  },
  {
    "url": "/weibo?q=%23%E8%80%81%E4%BA%BA%E6%91%94%E5%80%92%E7%9E%AC%E9%97%B4%E5%A4%A7%E5%93%A5%E6%BB%91%E9%93%B2%E6%8E%A5%E4%BD%8F%E5%A4%B4%E9%83%A8%23&t=31&band_rank=33&Refer=top",
    "title": "老人摔倒瞬间大哥滑铲接住头部"
  },
  {
    "url": "/weibo?q=%23%E5%A5%B3%E5%AD%90%E8%AF%95%E9%A9%BE%E5%86%B2%E8%BF%9B4S%E5%BA%97%E8%87%B4%E5%A4%9A%E8%BD%A6%E5%8F%97%E6%8D%9F%23&t=31&band_rank=6&Refer=top",
    "title": "女子试驾冲进4S店致多车受损"
  },
  {
    "url": "/weibo?q=%23%E4%B8%AD%E5%9B%BD%E4%B9%A1%E6%9D%91%E8%97%8F%E7%9D%80%E4%B8%80%E6%9C%AC%E5%B7%A8%E5%9E%8B%E9%A3%9F%E8%B0%B1%23&t=31&band_rank=34&Refer=top",
    "title": "中国乡村藏着一本巨型食谱"
  },
  {
    "url": "/weibo?q=%23%E5%BE%AE%E4%BF%A1%E6%8F%90%E7%8E%B0%E5%8F%AF%E4%BB%A5%E5%85%8D%E6%89%8B%E7%BB%AD%E8%B4%B9%E4%BA%86%23&t=31&band_rank=26&Refer=top",
    "title": "微信提现可以免手续费了"
  },
  {
    "url": "/weibo?q=%23%E7%A6%8F%E5%AE%9D%E7%9A%84%E5%A4%A7%E9%95%BF%E8%85%BF%E9%83%BD%E8%A6%81%E6%BA%A2%E5%87%BA%E5%B1%8F%E5%B9%95%E4%BA%86%23&t=31&band_rank=36&Refer=top",
    "title": "福宝的大长腿都要溢出屏幕了"
  },
  {
    "url": "/weibo?q=%23%E5%94%90%E5%AB%A3%E7%BD%97%E6%99%8B%E5%B8%A6%E5%A8%83%E9%80%9B%E8%BF%AA%E5%A3%AB%E5%B0%BC%23&t=31&band_rank=21&Refer=top",
    "title": "唐嫣罗晋带娃逛迪士尼"
  },
  {
    "url": "/weibo?q=%23%E5%86%9B%E5%AB%82%E5%B8%A6%E5%AD%A9%E5%AD%90%E8%BF%8E%E6%8E%A5%E4%B8%88%E5%A4%AB%E9%80%80%E5%BD%B9%E5%9B%9E%E5%AE%B6%23&t=31&band_rank=38&Refer=top",
    "title": "军嫂带孩子迎接丈夫退役回家"
  },
  {
    "url": "/weibo?q=%23%E5%9B%BD%E4%BA%A7%E8%80%81%E5%89%A7%E8%A2%ABAI%E7%88%86%E6%94%B9%E5%BE%97%E5%83%8F%E4%B8%AD%E6%AF%92%E4%BA%86%23&t=31&band_rank=16&Refer=top",
    "title": "国产老剧被AI爆改得像中毒了"
  },
  {
    "url": "/weibo?q=%23%E8%BF%99%E4%B8%80%E8%84%9A%E4%BC%B8%E5%BE%97%E5%A4%AA%E5%B8%85%E4%BA%86%23&t=31&band_rank=49&Refer=top",
    "title": "这一脚伸得太帅了"
  },
  {
    "url": "/weibo?q=%23%E9%99%88%E5%B0%8F%E6%98%A5%E7%9C%8B%E5%88%B0%E6%A2%85%E8%89%B3%E8%8A%B3%E7%9A%84%E8%BA%AB%E5%BD%B1%E5%93%AD%E4%BA%86%23&t=31&band_rank=42&Refer=top",
    "title": "陈小春看到梅艳芳的身影哭了"
  },
  {
    "url": "/weibo?q=%23%E5%8F%99%E5%88%A9%E4%BA%9A%E5%B0%86%E5%85%A8%E5%8A%9B%E4%BB%A5%E8%B5%B4%E5%9D%9A%E5%86%B3%E6%89%93%E5%87%BB%E5%A2%83%E5%86%85%E6%89%80%E6%9C%89%E6%9E%81%E7%AB%AF%E7%BB%84%E7%BB%87%23&t=31&band_rank=42&Refer=top",
    "title": "叙利亚将全力以赴坚决打击境内所有极端组织"
  },
  { "url": "/weibo?q=%E7%94%B3%E8%AE%BA%E7%AD%94%E6%A1%88&t=31&band_rank=43&Refer=top", "title": "申论答案" },
  {
    "url": "/weibo?q=%23%E8%89%BE%E6%BB%8B%E7%97%85%E6%97%A0%E7%97%87%E7%8A%B6%E6%9C%9F%E6%98%AF%E6%9C%80%E9%BA%BB%E7%83%A6%E7%9A%84%23&t=31&band_rank=44&Refer=top",
    "title": "艾滋病无症状期是最麻烦的"
  },
  {
    "url": "/weibo?q=%23%E5%AD%95%E5%A6%87%E6%83%B3%E6%9C%88%E5%AD%90%E6%9C%9F%E9%97%B4%E6%B4%97%E5%A4%B4%E8%A2%AB%E9%95%BF%E8%BE%88%E5%8C%85%E5%9B%B4%E5%8A%9D%E9%98%BB%23&t=31&band_rank=38&Refer=top",
    "title": "孕妇想月子期间洗头被长辈包围劝阻"
  },
  {
    "url": "/weibo?q=%23%E4%B8%A4%E6%89%91%E5%92%AC%E8%B7%AF%E4%BA%BA%E7%9A%84%E5%A4%A7%E5%9E%8B%E7%8A%AC%E4%B8%BB%E4%BA%BA%E4%B8%BA%E5%90%8C%E4%B8%80%E4%BA%BA%23&t=31&band_rank=47&Refer=top",
    "title": "两扑咬路人的大型犬主人为同一人"
  },
  {
    "url": "/weibo?q=%23TREASURE%E5%B0%86%E6%8D%A2%E9%98%9F%E9%95%BF%23&t=31&band_rank=4&Refer=top",
    "title": "TREASURE将换队长"
  },
  {
    "url": "/weibo?q=%E8%83%A1%E5%A4%8F%E8%A3%A4%E5%AD%90%E5%B4%A9%E4%BA%86&t=31&band_rank=49&Refer=top",
    "title": "胡夏裤子崩了"
  },
  {
    "url": "/weibo?q=%23%E9%99%88%E8%BF%91%E5%8D%97%E4%B8%BA%E5%91%A8%E8%8A%AF%E7%AB%B9%E5%8F%91%E5%A3%B0%23&t=31&band_rank=50&Refer=top",
    "title": "陈近南为周芯竹发声"
  },
  { "url": "/weibo?q=F1&t=31&band_rank=8&Refer=top", "title": "F1" },
  {
    "url": "/weibo?q=%23%E7%BE%8E%E5%9B%BD%E7%BB%8F%E9%94%80%E5%95%86%E5%BC%80%E5%A7%8B%E5%9B%A4%E9%85%92%E4%BA%86%23&t=31&band_rank=34&Refer=top",
    "title": "美国经销商开始囤酒了"
  },
  {
    "url": "/weibo?q=%23%E7%BE%8E%E5%9B%BD%E5%B0%8F%E4%BC%99%E8%AF%B4%E6%9D%A5%E5%8C%97%E4%BA%AC%E5%83%8F%E5%88%B0%E4%BA%86%E5%85%AC%E5%85%833000%E5%B9%B4%23&t=31&band_rank=35&Refer=top",
    "title": "美国小伙说来北京像到了公元3000年"
  },
  {
    "url": "/weibo?q=%23%E5%9B%BD%E9%98%B2%E9%83%A8%E8%B0%88%E4%B8%AD%E4%BF%84%E8%81%94%E5%90%88%E7%A9%BA%E4%B8%AD%E6%88%98%E7%95%A5%E5%B7%A1%E8%88%AA%23&t=31&band_rank=15&Refer=top",
    "title": "国防部谈中俄联合空中战略巡航"
  },
  {
    "url": "/weibo?q=%23%E6%9D%8E%E8%A1%8C%E4%BA%AE%E5%9B%A2%E9%98%9F%E7%A7%B0%E6%9A%82%E4%B8%8D%E4%BE%BF%E5%9B%9E%E5%BA%94%E7%BD%91%E5%8F%8B%E6%8A%B5%E5%88%B6%23&t=31&band_rank=10&Refer=top",
    "title": "李行亮团队称暂不便回应网友抵制"
  },
  {
    "url": "/weibo?q=%23%E5%91%A8%E8%8A%AF%E7%AB%B9%E8%AF%B4%E4%B8%8D%E5%A4%AA%E5%96%9C%E6%AC%A2%E8%A2%AB%E8%BF%87%E5%8E%BB%E6%8B%96%E4%BD%8F%23&t=31&band_rank=20&Refer=top",
    "title": "周芯竹说不太喜欢被过去拖住"
  },
  {
    "url": "/weibo?q=%23%E5%8F%B0%E6%B9%BE%E6%83%85%E4%BE%A3%E8%A2%AB%E6%9B%9D%E5%90%B8%E6%AF%92%E5%90%8E%E6%89%93%E6%AD%BB1%E5%B2%81%E5%A5%B3%E5%84%BF%23&t=31&band_rank=17&Refer=top",
    "title": "台湾情侣被曝吸毒后打死1岁女儿"
  },
  { "url": "/weibo?q=%E5%91%A8%E5%86%A0%E5%AE%87&t=31&band_rank=22&Refer=top", "title": "周冠宇" },
  {
    "url": "/weibo?q=%23%E5%91%A8%E5%86%A0%E5%AE%87%E5%85%A8%E5%9C%BA%E6%9C%80%E4%BD%B3%E8%BD%A6%E6%89%8B%23&t=31&band_rank=25&Refer=top",
    "title": "周冠宇全场最佳车手"
  },
  {
    "url": "/weibo?q=%23%E4%BD%8E%E7%A9%BA%E7%BB%8F%E6%B5%8E%E9%A1%B9%E7%9B%AE%E5%8A%A0%E9%80%9F%E8%90%BD%E5%9C%B0%23&t=31&band_rank=43&Refer=top",
    "title": "低空经济项目加速落地"
  },
  {
    "url": "/weibo?q=%E5%AD%99%E7%BA%A2%E9%9B%B7%E5%85%B3%E6%99%93%E5%BD%A4%E5%BC%A0%E8%89%BA%E5%85%B4%E5%A5%BD%E5%85%88%E7%94%9F%E5%8F%8B%E8%B0%8A&t=31&band_rank=45&Refer=top",
    "title": "孙红雷关晓彤张艺兴好先生友谊"
  },
  {
    "url": "/weibo?q=%23%E4%B8%AD%E6%96%B9%E5%AF%B9%E7%BE%8E%E6%96%B9%E5%AE%89%E6%8E%92%E8%B5%96%E6%B8%85%E5%BE%B7%E8%BF%87%E5%A2%83%E4%BA%88%E4%BB%A5%E4%B8%A5%E5%8E%89%E8%B0%B4%E8%B4%A3%23&t=31&band_rank=31&Refer=top",
    "title": "中方对美方安排赖清德过境予以严厉谴责"
  },
  {
    "url": "/weibo?q=%23%E5%A5%B3%E5%AD%90%E8%8A%B1%E8%BF%91%E4%BA%94%E4%B8%87%E7%9B%B8%E4%BA%B2%E4%B8%89%E6%AC%A1%E9%83%BD%E5%A4%B1%E8%B4%A5%E7%9B%BC%E9%80%80%E8%B4%B9%23&t=31&band_rank=36&Refer=top",
    "title": "女子花近五万相亲三次都失败盼退费"
  },
  {
    "url": "/weibo?q=%23%E6%88%91%E5%9B%BD%E9%A6%96%E4%B8%AA%E9%98%B6%E6%A2%AF%E5%BC%8F%E4%BD%8E%E7%A9%BA%E7%A9%BA%E5%9F%9F%E6%AD%A3%E5%BC%8F%E6%8A%95%E5%85%A5%E4%BD%BF%E7%94%A8%23&t=31&band_rank=43&Refer=top",
    "title": "我国首个阶梯式低空空域正式投入使用"
  },
  {
    "url": "/weibo?q=23%E5%B2%81%E6%B8%85%E5%8D%8E%E5%A5%B3%E5%8D%9A%E5%A3%AB%E5%AF%B9%E4%BA%BA%E7%94%9F%E7%9A%84%E7%9C%9F%E5%AE%9E%E6%84%9F%E5%8F%97&t=31&band_rank=12&Refer=top",
    "title": "23岁清华女博士对人生的真实感受"
  },
  { "url": "/weibo?q=%E5%8F%99%E5%88%A9%E4%BA%9A&t=31&band_rank=47&Refer=top", "title": "叙利亚" },
  {
    "url": "/weibo?q=%23%E4%B8%81%E7%A6%B9%E5%85%AE%E4%BB%8A%E5%A4%A9%E5%96%9D%E5%A5%B6%E8%8C%B6%E5%95%A6%23&t=31&band_rank=15&Refer=top",
    "title": "丁禹兮今天喝奶茶啦"
  },
  {
    "url": "/weibo?q=%23%E5%88%A9%E7%89%A9%E6%B5%A6vs%E6%9B%BC%E5%9F%8E%23&t=31&band_rank=20&Refer=top",
    "title": "利物浦vs曼城"
  },
  {
    "url": "/weibo?q=%E8%B5%B5%E9%9B%85%E8%8A%9D%E5%93%AD%E4%BA%86&t=31&band_rank=14&Refer=top",
    "title": "赵雅芝哭了"
  },
  {
    "url": "/weibo?q=%23%E8%BF%AA%E4%B8%BD%E7%83%AD%E5%B7%B4%E9%99%88%E9%A3%9E%E5%AE%87%E5%85%AC%E4%B8%BB%E6%8A%B1%E8%B7%AF%E9%80%8F%23&t=31&band_rank=29&Refer=top",
    "title": "迪丽热巴陈飞宇公主抱路透"
  },
  {
    "url": "/weibo?q=%E9%9F%B3%E4%B9%90%E8%8A%82%E4%B8%BB%E5%8A%9E%E5%81%9C%E6%AD%A2%E5%92%8C%E5%91%A8%E5%AF%86%E5%90%88%E4%BD%9C&t=31&band_rank=8&Refer=top",
    "title": "音乐节主办停止和周密合作"
  },
  {
    "url": "/weibo?q=%2390%E5%A4%9A%E5%90%8D%E8%89%BE%E6%BB%8B%E7%97%85%E6%82%A3%E5%84%BF%E6%9C%89%E4%B8%AA%E5%85%B1%E5%90%8C%E7%9A%84%E5%AE%B6%23&t=31&band_rank=48&Refer=top",
    "title": "90多名艾滋病患儿有个共同的家"
  },
  {
    "url": "/weibo?q=%23%E5%8F%99%E5%88%A9%E4%BA%9A%E5%8F%8D%E5%AF%B9%E6%B4%BE%E6%AD%A6%E8%A3%85%E6%94%BB%E5%85%A5%E9%98%BF%E5%8B%92%E9%A2%87%23&t=31&band_rank=42&Refer=top",
    "title": "叙利亚反对派武装攻入阿勒颇"
  },
  {
    "url": "/weibo?q=%23%E8%BF%90%E5%8A%A8%E5%91%98%E9%80%80%E5%BD%B9%E5%90%8E%E5%B1%95%E7%A4%BA%E8%87%AA%E5%B7%B1%E7%9A%84%E7%94%9F%E6%B4%BB%E5%BA%94%E5%B0%8A%E9%87%8D%23&t=31&band_rank=49&Refer=top",
    "title": "运动员退役后展示自己的生活应尊重"
  },
  {
    "url": "/weibo?q=%23%E5%A4%AE%E8%A7%86%E6%8B%8D%E7%9A%84%E7%BD%97%E4%BA%91%E7%86%99%23&t=31&band_rank=42&Refer=top",
    "title": "央视拍的罗云熙"
  },
  {
    "url": "/weibo?q=%E7%94%B5%E5%BD%B1%E5%A5%BD%E4%B8%9C%E8%A5%BF&t=31&band_rank=42&Refer=top",
    "title": "电影好东西"
  },
  {
    "url": "/weibo?q=%23%E6%82%A3%E8%80%85%E8%BF%BD%E5%BF%86%E5%9B%A0%E8%BD%A6%E7%A5%B8%E5%8E%BB%E4%B8%96%E7%9A%8445%E5%B2%81%E5%8C%BB%E7%94%9F%23&t=31&band_rank=40&Refer=top",
    "title": "患者追忆因车祸去世的45岁医生"
  },
  {
    "url": "/weibo?q=%E6%97%A5%E6%9C%AC%E6%89%87%E8%80%B3%E5%85%89%E9%A4%90%E5%8E%85&t=31&band_rank=30&Refer=top",
    "title": "日本扇耳光餐厅"
  },
  {
    "url": "/weibo?q=%23%E4%B9%B0%E6%AD%A6%E5%99%A8%E4%B9%B0%E4%B8%8D%E6%9D%A5%E5%AE%89%E5%85%A8%E4%BF%9D%E6%8A%A4%E8%B4%B9%E4%BF%9D%E4%B8%8D%E4%BA%86%E5%8F%B0%E7%8B%AC%23&t=31&band_rank=35&Refer=top",
    "title": "买武器买不来安全保护费保不了台独"
  },
  {
    "url": "/weibo?q=%E6%9C%B1%E5%BF%97%E9%91%AB%E5%89%AA%E5%A4%B4%E5%8F%91&t=31&band_rank=27&Refer=top",
    "title": "朱志鑫剪头发"
  },
  {
    "url": "/weibo?q=%E5%88%98%E5%AE%AA%E5%8D%8E%E6%BC%94%E5%94%B1%E4%BC%9A&t=31&band_rank=34&Refer=top",
    "title": "刘宪华演唱会"
  },
  {
    "url": "/weibo?q=%E7%9A%87%E9%A9%ACvs%E8%B5%AB%E5%A1%94%E8%8F%B2&t=31&band_rank=31&Refer=top",
    "title": "皇马vs赫塔菲"
  },
  {
    "url": "/weibo?q=%E5%B7%A6%E5%8F%B6%E5%9C%A8%E6%97%8B%E8%BD%AC%E6%9C%A8%E9%A9%AC%E5%89%8D%E8%B7%B3%E5%88%9D%E9%9B%AA&t=31&band_rank=20&Refer=top",
    "title": "左叶在旋转木马前跳初雪"
  },
  {
    "url": "/weibo?q=%23%E8%99%9E%E4%B9%A6%E6%AC%A3%E8%B6%85%E8%AF%9D%E8%A7%A3%E9%94%81%E9%92%BB3%23&t=31&band_rank=40&Refer=top",
    "title": "虞书欣超话解锁钻3"
  },
  {
    "url": "/weibo?q=%23%E5%8D%97%E4%BA%AC%E4%B8%BE%E8%A1%8C%E5%A4%A7%E5%B1%A0%E6%9D%80%E6%AD%BB%E9%9A%BE%E8%80%85%E5%AE%B6%E5%BA%AD%E7%A5%AD%E5%91%8A%E6%B4%BB%E5%8A%A8%23&t=31&band_rank=32&Refer=top",
    "title": "南京举行大屠杀死难者家庭祭告活动"
  },
  {
    "url": "/weibo?q=%23%E6%9B%BC%E8%81%94vs%E5%9F%83%E5%BC%97%E9%A1%BF%23&t=31&band_rank=45&Refer=top",
    "title": "曼联vs埃弗顿"
  },
  {
    "url": "/weibo?q=%232025%E5%BA%94%E5%BE%81%E6%8A%A5%E5%90%8D%E5%BC%80%E5%A7%8B%23&t=31&band_rank=50&Refer=top",
    "title": "2025应征报名开始"
  },
  {
    "url": "/weibo?q=%E6%9D%8E%E8%8E%8E%E6%97%BB%E5%AD%90%E5%8F%88%E5%8F%88%E5%8F%88%E5%92%8C%E5%91%A8%E7%AC%94%E7%95%85%E5%90%8C%E5%8F%B0%E4%BA%86&t=31&band_rank=20&Refer=top",
    "title": "李莎旻子又又又和周笔畅同台了"
  },
  {
    "url": "/weibo?q=%23%E6%9D%8E%E8%A1%8C%E4%BA%AE%E5%9B%A2%E9%98%9F%E5%A9%89%E6%8B%92%E9%87%87%E8%AE%BF%23&t=31&band_rank=13&Refer=top",
    "title": "李行亮团队婉拒采访"
  },
  {
    "url": "/weibo?q=%232024%E6%9C%80%E5%90%8E30%E5%A4%A9%E8%AF%B7%E4%BD%A0%E5%A5%BD%E5%A5%BD%E7%88%B1%E8%87%AA%E5%B7%B1%23&t=31&band_rank=45&Refer=top",
    "title": "2024最后30天请你好好爱自己"
  },
  {
    "url": "/weibo?q=%E9%87%91%E7%80%9A%20%E7%A5%96%E5%9B%BD%E7%9A%84%E5%8D%97%E6%B5%B7%E5%AE%9E%E5%9C%A8%E5%A4%AA%E5%A4%A7%E4%BA%86&t=31&band_rank=41&Refer=top",
    "title": "金瀚 祖国的南海实在太大了"
  },
  {
    "url": "/weibo?q=%23%E8%92%8B%E6%95%A6%E8%B1%AA%E4%BA%A4%E7%BB%99%E6%97%B6%E9%97%B4%E8%A7%A3%E7%AD%94%23&t=31&band_rank=23&Refer=top",
    "title": "蒋敦豪交给时间解答"
  },
  {
    "url": "/weibo?q=%23%E5%88%87%E5%AE%9E%E9%81%B5%E5%AE%88%E4%B8%80%E4%B8%AA%E4%B8%AD%E5%9B%BD%E5%8E%9F%E5%88%99%E6%98%AF%E5%8F%B0%E6%B5%B7%E5%92%8C%E5%B9%B3%E4%B9%8B%E7%A6%8F%23&t=31&band_rank=44&Refer=top",
    "title": "切实遵守一个中国原则是台海和平之福"
  },
  {
    "url": "/weibo?q=%23%E6%B3%B0%E5%9B%BD%E5%AD%95%E5%A6%87%E5%9D%A0%E5%B4%96%E6%A1%88%E5%8F%8C%E6%96%B9%E4%BB%8D%E6%9C%AA%E7%A6%BB%E5%A9%9A%23&t=31&band_rank=19&Refer=top",
    "title": "泰国孕妇坠崖案双方仍未离婚"
  },
  {
    "url": "/weibo?q=%2360%E5%A4%9A%E5%B9%B4%E4%BB%96%E4%BB%AC%E8%AF%95%E5%B0%84%E6%95%B0%E5%8D%83%E6%9E%9A%E5%AF%BC%E5%BC%B9%23&t=31&band_rank=49&Refer=top",
    "title": "60多年他们试射数千枚导弹"
  },
  {
    "url": "/weibo?q=%23%E6%9D%8E%E8%A1%8C%E4%BA%AE%E5%95%86%E6%BC%94%E5%86%8D%E6%AC%A1%E9%81%AD%E6%8A%B5%E5%88%B6%23&t=31&band_rank=18&Refer=top",
    "title": "李行亮商演再次遭抵制"
  },
  {
    "url": "/weibo?q=%23%E5%82%85%E9%A6%96%E5%B0%94%E8%AF%B4%E6%88%91%E6%98%AF%E5%AE%B9%E8%B2%8C%E6%94%BB%E5%87%BB%E7%9A%84%E9%87%8D%E7%82%B9%E5%AF%B9%E8%B1%A1%23&t=31&band_rank=20&Refer=top",
    "title": "傅首尔说我是容貌攻击的重点对象"
  },
  { "url": "/weibo?q=N1%E7%AD%94%E6%A1%88&t=31&band_rank=25&Refer=top", "title": "N1答案" },
  {
    "url": "/weibo?q=%E5%8D%8E%E6%99%A8%E5%AE%87%E8%B9%A6%E4%B8%A2%E4%BA%86%E4%B8%80%E4%B8%AA31%E4%B8%87%E7%9A%84%E8%80%B3%E9%92%89&t=31&band_rank=32&Refer=top",
    "title": "华晨宇蹦丢了一个31万的耳钉"
  },
  {
    "url": "/weibo?q=%23%E5%BC%A0%E5%A9%A7%E4%BB%AA%E7%BC%87%E5%85%B0%E8%AF%95%E5%A6%86%23&t=31&band_rank=28&Refer=top",
    "title": "张婧仪缇兰试妆"
  },
  {
    "url": "/weibo?q=%23%E7%8E%8B%E5%AE%89%E5%AE%87%E6%8B%89%E7%9D%80%E9%87%91%E6%99%A8%E6%92%92%E5%A8%87%23&t=31&band_rank=37&Refer=top",
    "title": "王安宇拉着金晨撒娇"
  },
  {
    "url": "/weibo?q=%23%E5%9B%BD%E8%80%83%E7%AC%94%E8%AF%95%E5%AE%9E%E9%99%85%E5%8F%82%E8%80%83258.6%E4%B8%87%E4%BA%BA%23&t=31&band_rank=37&Refer=top",
    "title": "国考笔试实际参考258.6万人"
  },
  { "url": "/weibo?q=%E7%8E%8B%E5%AE%89%E5%AE%87%E5%A5%BD%E5%B8%85&t=31&band_rank=7&Refer=top", "title": "王安宇好帅" },
  {
    "url": "/weibo?q=%23%E5%BC%A0%E6%B3%BD%E7%A6%B9%E5%8F%91%E4%BA%8618%E5%AE%AB%E6%A0%BC%23&t=31&band_rank=24&Refer=top",
    "title": "张泽禹发了18宫格"
  },
  {
    "url": "/weibo?q=%23%E6%96%B0%E4%BA%BA%E6%89%93%E9%87%8E%E5%90%91%E9%B1%BC%23&t=31&band_rank=25&Refer=top",
    "title": "新人打野向鱼"
  },
  {
    "url": "/weibo?q=%23%E6%88%90%E9%83%BD%E6%B7%B7%E5%9B%A2%E5%9B%BD%E4%B9%92%E9%9B%B6%E5%B0%81%E6%BE%B3%E5%A4%A7%E5%88%A9%E4%BA%9A%23&t=31&band_rank=35&Refer=top",
    "title": "成都混团国乒零封澳大利亚"
  },
  {
    "url": "/weibo?q=%23%E8%B5%B5%E9%9C%B2%E6%80%9D%E5%8F%91%E6%96%87%E5%AE%A3%E4%BC%A0%E8%9C%80%E9%94%A6%E4%BA%BA%E5%AE%B6%23&t=31&band_rank=40&Refer=top",
    "title": "赵露思发文宣传蜀锦人家"
  },
  {
    "url": "/weibo?q=%23%E9%99%88%E5%93%B2%E8%BF%9C%E4%B8%BE125%E5%85%AC%E6%96%A4%E6%9D%A0%E9%93%83%23&t=31&band_rank=26&Refer=top",
    "title": "陈哲远举125公斤杠铃"
  },
  { "url": "/weibo?q=%23%E5%A4%9A%E5%A4%9A%E4%BD%B3%E9%91%AB%23&t=31&band_rank=49&Refer=top", "title": "多多佳鑫" },
  {
    "url": "/weibo?q=%23%E5%85%A8%E5%9C%86%E4%BD%91%E7%BB%9D%E7%BE%8E%E6%B0%9B%E5%9B%B4%23&t=31&band_rank=28&Refer=top",
    "title": "全圆佑绝美氛围"
  },
  { "url": "/weibo?q=%E5%B7%A5%E4%BD%9C%E6%8C%87%E5%8D%97&t=31&band_rank=25&Refer=top", "title": "工作指南" },
  { "url": "/weibo?q=%E7%99%BD%E6%A1%83%E6%98%9F%E5%BA%A7&t=31&band_rank=30&Refer=top", "title": "白桃星座" },
  { "url": "/weibo?q=%23%E8%A8%80%E8%AF%AD%E7%BC%A9%E5%87%8F%23&t=31&band_rank=25&Refer=top", "title": "言语缩减" },
  {
    "url": "/weibo?q=%E8%B0%AD%E6%9D%BE%E9%9F%B5%E6%88%91%E9%82%A3%E5%8F%AF%E7%88%B1%E7%9A%84%E5%AE%9D%E5%AE%9D%E5%A7%90&t=31&band_rank=42&Refer=top",
    "title": "谭松韵我那可爱的宝宝姐"
  },
  {
    "url": "/weibo?q=%23%E5%85%B3%E6%99%93%E5%BD%A4%E7%BB%99%E5%BC%A0%E8%89%BA%E5%85%B4%E9%9F%B3%E4%B9%90%E8%AF%9D%E5%89%A7%E6%89%93call%23&t=31&band_rank=46&Refer=top",
    "title": "关晓彤给张艺兴音乐话剧打call"
  },
  {
    "url": "/weibo?q=%23%E5%9B%BD%E8%80%83%E7%AC%94%E8%AF%95%E7%BB%93%E6%9D%9F%23&t=31&band_rank=47&Refer=top",
    "title": "国考笔试结束"
  },
  {
    "url": "/weibo?q=%23%E7%9F%A5%E6%83%85%E4%BA%BA%E5%9B%9E%E5%BA%94%E8%A5%BF%E5%AE%89%E5%A4%A7%E5%9E%8B%E7%8A%AC%E6%89%91%E5%92%AC%E4%BA%8B%E4%BB%B6%23&t=31&band_rank=39&Refer=top",
    "title": "知情人回应西安大型犬扑咬事件"
  },
  {
    "url": "/weibo?q=%2345%E5%B2%81%E8%83%B8%E5%A4%96%E7%A7%91%E4%B8%BB%E4%BB%BB%E8%BD%A6%E7%A5%B8%E5%8E%BB%E4%B8%96%E5%AE%B6%E5%B1%9E%E5%8F%91%E5%A3%B0%23&t=31&band_rank=41&Refer=top",
    "title": "45岁胸外科主任车祸去世家属发声"
  },
  {
    "url": "/weibo?q=%23%E6%9C%B4%E5%BD%A9%E8%8B%B1%E5%89%A7%E9%80%8FBLACKPINK%E6%98%8E%E5%B9%B4%E5%9B%9E%E5%BD%92%23&t=31&band_rank=43&Refer=top",
    "title": "朴彩英剧透BLACKPINK明年回归"
  },
  {
    "url": "/weibo?q=%23%E7%8E%8B%E6%A5%9A%E9%92%A6%E8%B5%9B%E5%90%8E%E6%8F%90%E9%86%92%E9%98%9F%E5%8F%8B%E6%94%B6%E5%A5%BD%E7%A9%BA%E7%93%B6%23&t=31&band_rank=44&Refer=top",
    "title": "王楚钦赛后提醒队友收好空瓶"
  },
  { "url": "/weibo?q=%E7%8E%8B%E6%9B%BC%E6%98%B1VOGUE&t=31&band_rank=46&Refer=top", "title": "王曼昱VOGUE" },
  { "url": "/weibo?q=%E5%8C%97%E4%BA%AC%E6%99%9A%E9%9C%9E&t=31&band_rank=49&Refer=top", "title": "北京晚霞" },
  {
    "url": "/weibo?q=%E8%BF%99%E4%B8%AA%E5%A8%84%E5%AD%90%E5%BB%BA%E8%AE%AE%E5%A4%9A%E6%8D%85%E5%87%A0%E6%AC%A1&t=31&band_rank=50&Refer=top",
    "title": "这个娄子建议多捅几次"
  }
]
